{
  "CM45系列抗光干扰槽型光电开关 光电传感器": {
    "产品名称": "CM45系列抗光干扰槽型光电开关 光电传感器",
    "产品图片": "http://www.coolmay.com/kindeditor/attached/image/myUpload/GbmKYz202185100911.jpg",
    "产品特点": "http://www.coolmay.com/kindeditor/attached/image/20210918/20210918135142_1939.jpg;1.有4种不同的安装方式K型，T型,Y型，L型;2.感应不透光的物体，检测距离5mm;3.抗光干扰性强,可以在强光环境下正常工作；3.双灯指示，绿灯强暗表示入光和遮光状态，红灯表示输出转化状态；4.电气接线为直流4线式连接；粉线接正极可切换输出状态；5.采用台湾芯片，响应频率高，可达4000-5000Hz;6.外壳防护等级为IP65;7.带短路，极性和浪涌保护功能；8.采用特殊的PC材质；9.结构紧凑，安装尺寸与欧姆龙67系列和松下45系列相同，可直接替代它们；10.符合标准GB/T14048.10",
    "产品参数": {
      "型 号": {
        "K45": {
          "NPN输出": "CMK45",
          "PNP输出": "CMK45P",
          "检测距离": "5mm槽型对射",
          "响应频率": "4000Hz",
          "工作电压": "5～24VDC",
          "重复精度": "0.01mm以下",
          "应差距离": "0.02mm～0.05mm",
          "最小检测物": "0.8mmX1.2mm 不透明物体",
          "负载电流": "<100mA",
          "残余电压": "0.5V以下（10mA时）/0.7V以下（100mA时）",
          "损耗电流": "<12mA",
          "输出动作": "入光时NO/遮光时NO",
          "指示灯": "绿灯：入光时灯亮，遮光时灯暗;;红灯：有输出(ON)时灯亮，无输出(OFF)时灯灭，过载时，红灯闪烁",
          "保护": "短路保护，极性保护，浪涌保护",
          "环境温度": "-5℃～+55℃",
          "环境照度": "受光面 荧光灯或LED:3000Lx以下，白炽灯：1000Lx以下",
          "防护等级": "IP65",
          "连接方式": "φ2.8 1m PVC电缆(四线）",
          "外壳材质": "特殊PC",
          "重量": "约13g"
        },
        "L45": {
          "型 号": "L45",
          "NPN输出": "CML45",
          "PNP输出": "CML45P",
          "检测距离": "5mm槽型对射",
          "响应频率": "4000Hz",
          "工作电压": "5～24VDC",
          "重复精度": "0.01mm以下",
          "应差距离": "0.02mm～0.05mm",
          "最小检测物": "0.8mmX1.2mm 不透明物体",
          "负载电流": "<100mA",
          "残余电压": "0.5V以下（10mA时）/0.7V以下（100mA时）",
          "损耗电流": "<12mA",
          "输出动作": "入光时NO/遮光时NO",
          "指示灯": "绿灯：入光时灯亮，遮光时灯暗;;红灯：有输出(ON)时灯亮，无输出(OFF)时灯灭，过载时，红灯闪烁",
          "保护": "短路保护，极性保护，浪涌保护",
          "环境温度": "-5℃～+55℃",
          "环境照度": "受光面 荧光灯或LED:3000Lx以下，白炽灯：1000Lx以下",
          "防护等级": "IP65",
          "连接方式": "φ2.8 1m PVC电缆(四线）",
          "外壳材质": "特殊PC",
          "重量": "约13g"
        },
        "T45": {
          "型 号": "T45",
          "NPN输出": "CMT45",
          "PNP输出": "CMT45P",
          "检测距离": "5mm槽型对射",
          "响应频率": "4000Hz",
          "工作电压": "5～24VDC",
          "重复精度": "0.01mm以下",
          "应差距离": "0.02mm～0.05mm",
          "最小检测物": "0.8mmX1.2mm 不透明物体",
          "负载电流": "<100mA",
          "残余电压": "0.5V以下（10mA时）/0.7V以下（100mA时）",
          "损耗电流": "<12mA",
          "输出动作": "入光时NO/遮光时NO",
          "指示灯": "绿灯：入光时灯亮，遮光时灯暗;;红灯：有输出(ON)时灯亮，无输出(OFF)时灯灭，过载时，红灯闪烁",
          "保护": "短路保护，极性保护，浪涌保护",
          "环境温度": "-5℃～+55℃",
          "环境照度": "受光面 荧光灯或LED:3000Lx以下，白炽灯：1000Lx以下",
          "防护等级": "IP65",
          "连接方式": "φ2.8 1m PVC电缆(四线）",
          "外壳材质": "特殊PC",
          "重量": "约13g"
        },
        "Y45": {
          "型 号": "Y45",
          "NPN输出": "CMY45",
          "PNP输出": "CMY45P",
          "检测距离": "5mm槽型对射",
          "响应频率": "4000Hz",
          "工作电压": "5～24VDC",
          "重复精度": "0.01mm以下",
          "应差距离": "0.02mm～0.05mm",
          "最小检测物": "0.8mmX1.2mm 不透明物体",
          "负载电流": "<100mA",
          "残余电压": "0.5V以下（10mA时）/0.7V以下（100mA时）",
          "损耗电流": "<12mA",
          "输出动作": "入光时NO/遮光时NO",
          "指示灯": "绿灯：入光时灯亮，遮光时灯暗;;红灯：有输出(ON)时灯亮，无输出(OFF)时灯灭，过载时，红灯闪烁",
          "保护": "短路保护，极性保护，浪涌保护",
          "环境温度": "-5℃～+55℃",
          "环境照度": "受光面 荧光灯或LED:3000Lx以下，白炽灯：1000Lx以下",
          "防护等级": "IP65",
          "连接方式": "φ2.8 1m PVC电缆(四线）",
          "外壳材质": "特殊PC",
          "重量": "约13g"
        }
      }
    },
    "安装尺寸": {
      "text": "",
      "img": ""
    }
  },
  "普通槽型光电传感器": {
    "产品名称": "普通槽型光电传感器",
    "产品图片": "http://www.coolmay.com/kindeditor/attached/image/myUpload/INmn3z202185100951.jpg",
    "产品特点": "1.有5种不同的安装方式K型，T型,Y型，L型,F型;与欧姆龙67系列相同的外形与安装尺寸；2.对检测物的范围广，金属与非金属物体都可以被感应，检测距离5mm;3.响应频率不小于1000Hz(平均不低于3000Hz）；3.指示灯红色，红灯表示输出转化状态；4.电气接线为直流4线式连接；白线接正极可切换输出状态；5.外壳防护等级为IP65;6.带短路，极性和浪涌保护功能；7.采用PC材质；8.安装尺寸与欧姆龙67系列和松下45系列相同，可直接替代它们；9.符合标准GB/T14048.10",
    "产品参数": {
      "型 号": {
        "CMSX670": {
          "型 号": "CMSX670",
          "指示灯模式": "遮光时;灯亮",
          "NPN输出": "CMSX670A",
          "PNP输出": "CMSX670R",
          "检测距离": "5mm槽型对射",
          "响应频率": "3000Hz",
          "工作电压": "5～24VDC",
          "应差距离": "0.025mm",
          "最小检测物": "0.8mmX1.2mm 不透明物体",
          "负载电流": "<100mA",
          "电压降": "<2.5V",
          "电流损耗": "<12mA",
          "指示灯": "红灯：有输出（ON)时灯亮，无输出(OFF)时灯灭",
          "保护": "短路保护，极性保护，浪涌保护",
          "环境温度": "-5℃～+55℃",
          "环境照度": "受光面 荧光灯或LED:2000Lx以下，白炽灯：800Lx以下",
          "防护等级": "IP67",
          "连接方式": "φ2.8 2m PVC电缆(四线）",
          "外壳材质": "特殊处理的PC",
          "重量": "约22g"
        },
        "CMSX671": {
          "型 号": "CMSX671",
          "指示灯模式": "遮光时;灯亮",
          "NPN输出": "CMSX671A",
          "PNP输出": "CMSX671R",
          "检测距离": "5mm槽型对射",
          "响应频率": "3000Hz",
          "工作电压": "5～24VDC",
          "应差距离": "0.025mm",
          "最小检测物": "0.8mmX1.2mm 不透明物体",
          "负载电流": "<100mA",
          "电压降": "<2.5V",
          "电流损耗": "<12mA",
          "指示灯": "红灯：有输出（ON)时灯亮，无输出(OFF)时灯灭",
          "保护": "短路保护，极性保护，浪涌保护",
          "环境温度": "-5℃～+55℃",
          "环境照度": "受光面 荧光灯或LED:2000Lx以下，白炽灯：800Lx以下",
          "防护等级": "IP67",
          "连接方式": "φ2.8 2m PVC电缆(四线）",
          "外壳材质": "特殊处理的PC",
          "重量": "约22g"
        },
        "CMSX672": {
          "型 号": "CMSX672",
          "指示灯模式": "遮光时;灯亮",
          "NPN输出": "CMSX672A",
          "PNP输出": "CMSX672R",
          "检测距离": "5mm槽型对射",
          "响应频率": "3000Hz",
          "工作电压": "5～24VDC",
          "应差距离": "0.025mm",
          "最小检测物": "0.8mmX1.2mm 不透明物体",
          "负载电流": "<100mA",
          "电压降": "<2.5V",
          "电流损耗": "<12mA",
          "指示灯": "红灯：有输出（ON)时灯亮，无输出(OFF)时灯灭",
          "保护": "短路保护，极性保护，浪涌保护",
          "环境温度": "-5℃～+55℃",
          "环境照度": "受光面 荧光灯或LED:2000Lx以下，白炽灯：800Lx以下",
          "防护等级": "IP67",
          "连接方式": "φ2.8 2m PVC电缆(四线）",
          "外壳材质": "特殊处理的PC",
          "重量": "约22g"
        },
        "CMSX673": {
          "型 号": "CMSX673",
          "指示灯模式": "遮光时;灯亮",
          "NPN输出": "CMSX673A",
          "PNP输出": "CMSX673R",
          "检测距离": "5mm槽型对射",
          "响应频率": "3000Hz",
          "工作电压": "5～24VDC",
          "应差距离": "0.025mm",
          "最小检测物": "0.8mmX1.2mm 不透明物体",
          "负载电流": "<100mA",
          "电压降": "<2.5V",
          "电流损耗": "<12mA",
          "指示灯": "红灯：有输出（ON)时灯亮，无输出(OFF)时灯灭",
          "保护": "短路保护，极性保护，浪涌保护",
          "环境温度": "-5℃～+55℃",
          "环境照度": "受光面 荧光灯或LED:2000Lx以下，白炽灯：800Lx以下",
          "防护等级": "IP67",
          "连接方式": "φ2.8 2m PVC电缆(四线）",
          "外壳材质": "特殊处理的PC",
          "重量": "约22g"
        },
        "CMSX674": {
          "型 号": "CMSX674",
          "指示灯模式": "遮光时;灯亮",
          "NPN输出": "CMSX674A",
          "PNP输出": "CMSX674R",
          "检测距离": "5mm槽型对射",
          "响应频率": "3000Hz",
          "工作电压": "5～24VDC",
          "应差距离": "0.025mm",
          "最小检测物": "0.8mmX1.2mm 不透明物体",
          "负载电流": "<100mA",
          "电压降": "<2.5V",
          "电流损耗": "<12mA",
          "指示灯": "红灯：有输出（ON)时灯亮，无输出(OFF)时灯灭",
          "保护": "短路保护，极性保护，浪涌保护",
          "环境温度": "-5℃～+55℃",
          "环境照度": "受光面 荧光灯或LED:2000Lx以下，白炽灯：800Lx以下",
          "防护等级": "IP67",
          "连接方式": "φ2.8 2m PVC电缆(四线）",
          "外壳材质": "特殊处理的PC",
          "重量": "约22g"
        }
      }
    },
    "安装尺寸": {
      "text": "CMSX670              CMSX671CMSX672             CMSX673CMSX674",
      "img": "http://www.coolmay.com/kindeditor/attached/image/20210816/20210816161405_2315.jpg;http://www.coolmay.com/kindeditor/attached/image/20210816/20210816161453_1610.jpg;http://www.coolmay.com/kindeditor/attached/image/20210816/20210816161657_7361.jpg;http://www.coolmay.com/kindeditor/attached/image/20210816/20210816161733_4545.jpg;http://www.coolmay.com/kindeditor/attached/image/20210816/20210816161852_0315.jpg;"
    }
  },
  "标准圆柱型电感传感器": {
    "产品名称": "标准圆柱型电感传感器",
    "产品图片": "http://www.coolmay.com/kindeditor/attached/image/myUpload/azmhEe202185101020.jpg",
    "产品特点": "1.M8-M30标准圆柱型螺管;2.感应磁性的金属物体，检测距离1-15mm;3.指示灯显示黄色；4.电气接线为直流3线式连接；5.外壳防护等级为IP67;6.带短路，极性和浪涌保护功能；7.采用不锈钢材质；8.符合标准GB/T14048.10",
    "产品参数": {
      "型号": {
        "LM8-A": {
          "安装方式": "埋入式",
          "直流型": {
            "NPN": {
              "NO": "LM8P1DD1-A",
              "NC": "LM8P1DD2-A"
            },
            "PNP": {
              "NO": "LM8P1DD1-A",
              "NC": "LM8P1DD2-A"
            },
            "二线": {
              "NO": "LM8P1DD1-A",
              "NC": "LM8P1DD2-A"
            }
          },
          "检测距离": "1.0mm±10%",
          "响应频率": ">2000Hz",
          "工作电压": "10-30VDC",
          "指示灯": "黄色LED",
          "温漂": "<10%Sr",
          "负载电流": "<150mA",
          "漏电流": "<0.1mA",
          "电压降": "<1.5V",
          "电流损耗": "<10mA",
          "冲击耐压": "1000VAC  50/60Hz 60s",
          "回差": "≤15%Sr",
          "重复精度": "≤3%Sr",
          "保护": "短路保护 ，极性，浪涌保护",
          "环境温度": "-25℃～+70℃",
          "防护等级": "IP67",
          "连接方式": "2m  PVC电缆(三线）",
          "外壳材质": "黄铜镀镍",
          "感应面材质": "PBT"
        },
        "LM8-A_(1)": {
          "安装方式": "非埋入式",
          "直流型": {
            "NPN": {
              "NO": "LM8F2DD1-A",
              "NC": "LM8F2DD2-A"
            },
            "PNP": {
              "NO": "LM8F2DD1-A",
              "NC": "LM8F2DD2-A"
            },
            "二线": {
              "NO": "LM8F2DD1-A",
              "NC": "LM8F2DD2-A"
            }
          },
          "检测距离": "2mm±10%",
          "响应频率": ">1000Hz",
          "工作电压": "10-30VDC",
          "指示灯": "黄色LED",
          "温漂": "<10%Sr",
          "负载电流": "<150mA",
          "漏电流": "<0.1mA",
          "电压降": "<1.5V",
          "电流损耗": "<10mA",
          "冲击耐压": "1000VAC  50/60Hz 60s",
          "回差": "≤15%Sr",
          "重复精度": "≤3%Sr",
          "保护": "短路保护 ，极性，浪涌保护",
          "环境温度": "-25℃～+70℃",
          "防护等级": "IP67",
          "连接方式": "2m  PVC电缆(三线）",
          "外壳材质": "黄铜镀镍",
          "感应面材质": "PBT"
        },
        "LM12-A": {
          "安装方式": "埋入式",
          "直流型": {
            "NPN": {
              "NO": "LM12P2DD1-A",
              "NC": "LM12P2DD2-A"
            },
            "PNP": {
              "NO": "LM12P2DD1-A",
              "NC": "LM12P2DD2-A"
            },
            "二线": {
              "NO": "LM12P2DD1-A",
              "NC": "LM12P2DD2-A"
            }
          },
          "检测距离": "2mm±10%",
          "响应频率": ">1500Hz",
          "工作电压": "10-30VDC",
          "指示灯": "黄色LED",
          "温漂": "<10%Sr",
          "负载电流": "<150mA",
          "漏电流": "<0.1mA",
          "电压降": "<1.5V",
          "电流损耗": "<10mA",
          "冲击耐压": "1000VAC  50/60Hz 60s",
          "回差": "≤15%Sr",
          "重复精度": "≤3%Sr",
          "保护": "短路保护 ，极性，浪涌保护",
          "环境温度": "-25℃～+70℃",
          "防护等级": "IP67",
          "连接方式": "2m  PVC电缆(三线）",
          "外壳材质": "黄铜镀镍",
          "感应面材质": "PBT"
        },
        "LM12-A_(1)": {
          "安装方式": "非埋入式",
          "直流型": {
            "NPN": {
              "NO": "LM8F4DD1-A",
              "NC": "LM8F4DD2-A"
            },
            "PNP": {
              "NO": "LM8F4DD1-A",
              "NC": "LM8F4DD2-A"
            },
            "二线": {
              "NO": "LM8F4DD1-A",
              "NC": "LM8F4DD2-A"
            }
          },
          "检测距离": "4mm±10%",
          "响应频率": ">800Hz",
          "工作电压": "10-30VDC",
          "指示灯": "黄色LED",
          "温漂": "<10%Sr",
          "负载电流": "<150mA",
          "漏电流": "<0.1mA",
          "电压降": "<1.5V",
          "电流损耗": "<10mA",
          "冲击耐压": "1000VAC  50/60Hz 60s",
          "回差": "≤15%Sr",
          "重复精度": "≤3%Sr",
          "保护": "短路保护 ，极性，浪涌保护",
          "环境温度": "-25℃～+70℃",
          "防护等级": "IP67",
          "连接方式": "2m  PVC电缆(三线）",
          "外壳材质": "黄铜镀镍",
          "感应面材质": "PBT"
        },
        "LM18-A": {
          "安装方式": "埋入式",
          "直流型": {
            "NPN": {
              "NO": "LM18P5DD1-A",
              "NC": "LM18P5DD2-A"
            },
            "PNP": {
              "NO": "LM18P5DD1-A",
              "NC": "LM18P5DD2-A"
            },
            "二线": {
              "NO": "LM18P5DD1-A",
              "NC": "LM18P5DD2-A"
            }
          },
          "检测距离": "5mm±10%",
          "响应频率": ">600Hz",
          "工作电压": "10-30VDC",
          "指示灯": "黄色LED",
          "温漂": "<10%Sr",
          "负载电流": "<150mA",
          "漏电流": "<0.1mA",
          "电压降": "<1.5V",
          "电流损耗": "<10mA",
          "冲击耐压": "1000VAC  50/60Hz 60s",
          "回差": "≤15%Sr",
          "重复精度": "≤3%Sr",
          "保护": "短路保护 ，极性，浪涌保护",
          "环境温度": "-25℃～+70℃",
          "防护等级": "IP67",
          "连接方式": "2m  PVC电缆(三线）",
          "外壳材质": "黄铜镀镍",
          "感应面材质": "PBT"
        },
        "LM18-A_(1)": {
          "安装方式": "非埋入式",
          "直流型": {
            "NPN": {
              "NO": "LM18F8DD1-A",
              "NC": "LM18F8DD2-A"
            },
            "PNP": {
              "NO": "LM18F8DD1-A",
              "NC": "LM18F8DD2-A"
            },
            "二线": {
              "NO": "LM18F8DD1-A",
              "NC": "LM18F8DD2-A"
            }
          },
          "检测距离": "8mm±10%",
          "响应频率": ">400Hz",
          "工作电压": "10-30VDC",
          "指示灯": "黄色LED",
          "温漂": "<10%Sr",
          "负载电流": "<150mA",
          "漏电流": "<0.1mA",
          "电压降": "<1.5V",
          "电流损耗": "<10mA",
          "冲击耐压": "1000VAC  50/60Hz 60s",
          "回差": "≤15%Sr",
          "重复精度": "≤3%Sr",
          "保护": "短路保护 ，极性，浪涌保护",
          "环境温度": "-25℃～+70℃",
          "防护等级": "IP67",
          "连接方式": "2m  PVC电缆(三线）",
          "外壳材质": "黄铜镀镍",
          "感应面材质": "PBT"
        },
        "LM30-A": {
          "安装方式": "埋入式",
          "直流型": {
            "NPN": {
              "NO": "LM30P10DD1-A",
              "NC": "LM30P10DD2-A"
            },
            "PNP": {
              "NO": "LM30P10DD1-A",
              "NC": "LM30P10DD2-A"
            },
            "二线": {
              "NO": "LM30P10DD1-A",
              "NC": "LM30P10DD2-A"
            }
          },
          "检测距离": "10mm±10%",
          "响应频率": ">400Hz",
          "工作电压": "10-30VDC",
          "指示灯": "黄色LED",
          "温漂": "<10%Sr",
          "负载电流": "<150mA",
          "漏电流": "<0.1mA",
          "电压降": "<1.5V",
          "电流损耗": "<10mA",
          "冲击耐压": "1000VAC  50/60Hz 60s",
          "回差": "≤15%Sr",
          "重复精度": "≤3%Sr",
          "保护": "短路保护 ，极性，浪涌保护",
          "环境温度": "-25℃～+70℃",
          "防护等级": "IP67",
          "连接方式": "2m  PVC电缆(三线）",
          "外壳材质": "黄铜镀镍",
          "感应面材质": "PBT"
        },
        "LM30-A_(1)": {
          "安装方式": "非埋入式",
          "直流型": {
            "NPN": {
              "NO": "LM30F15DD1-A",
              "NC": "LM30F15DD2-A"
            },
            "PNP": {
              "NO": "LM30F15DD1-A",
              "NC": "LM30F15DD2-A"
            },
            "二线": {
              "NO": "LM30F15DD1-A",
              "NC": "LM30F15DD2-A"
            }
          },
          "检测距离": "15mm±10%",
          "响应频率": ">100Hz",
          "工作电压": "10-30VDC",
          "指示灯": "黄色LED",
          "温漂": "<10%Sr",
          "负载电流": "<150mA",
          "漏电流": "<0.1mA",
          "电压降": "<1.5V",
          "电流损耗": "<10mA",
          "冲击耐压": "1000VAC  50/60Hz 60s",
          "回差": "≤15%Sr",
          "重复精度": "≤3%Sr",
          "保护": "短路保护 ，极性，浪涌保护",
          "环境温度": "-25℃～+70℃",
          "防护等级": "IP67",
          "连接方式": "2m  PVC电缆(三线）",
          "外壳材质": "黄铜镀镍",
          "感应面材质": "PBT"
        }
      }
    },
    "安装尺寸": {
      "text": "LM8-A埋入式LM12-A埋入式LM12-A非埋入式LM18-A埋入式LM18-A非埋入式LM30-A埋入式LM30-A非埋入式",
      "img": "http://www.coolmay.com/kindeditor/attached/image/20210816/20210816164044_3196.jpg;http://www.coolmay.com/kindeditor/attached/image/20210816/20210816165212_3527.jpg;http://www.coolmay.com/kindeditor/attached/image/20210816/20210816165240_3392.jpg;http://www.coolmay.com/kindeditor/attached/image/20210816/20210816165427_2659.jpg;http://www.coolmay.com/kindeditor/attached/image/20210816/20210816165449_5457.jpg;http://www.coolmay.com/kindeditor/attached/image/20210816/20210816165514_1867.jpg;http://www.coolmay.com/kindeditor/attached/image/20210816/20210816165524_4048.jpg;"
    }
  },
  "超细圆柱电感式传感器": {
    "产品名称": "超细圆柱电感式传感器",
    "产品图片": "http://www.coolmay.com/kindeditor/attached/image/myUpload/FAnboT202185101036.jpg",
    "产品特点": "1.体积小，使用在狭窄的空间;2.感应磁性的金属物体，检测距离0.6-1mm;3.指示灯显示黄色；4.电气接线为直流3线式连接；5.外壳防护等级为IP67;6.带极性和浪涌保护功能；7.采用不锈钢材质；8.符合标准GB/T14048.10",
    "产品参数": {
      "型 号": {
        "M5": {
          "安装方式": "埋入式",
          "NPN": {
            "NO": "LM5GP0.8DN1",
            "NC": "LM5GP0.8DN2"
          },
          "PNP": {
            "NO": "LM5GP0.8DP1",
            "NC": "LM5GP0.8DP2"
          },
          "检测距离": "0.8mm±10%",
          "响应频率": "2K",
          "工作电压": "10-30VDC",
          "指示灯": "黄色LED",
          "温漂": "<10%Sr",
          "负载电流": "<150mA",
          "漏电流": "<0.1mA",
          "电压降": "<1.5V",
          "电流损耗": "<10mA",
          "冲击耐压": "1000VAC  50/60Hz 60s",
          "回差": "≤15%Sr",
          "重复精度": "≤5%Sr",
          "保护": "短路保护，极性保护，浪涌保护",
          "环境温度": "-25℃～+70℃",
          "防护等级": "IP67",
          "连接方式": "2m  PVC电缆(三线）",
          "外壳材质": "不锈钢",
          "感应面材质": "PA66"
        },
        "M5_(1)": {
          "安装方式": "埋入式",
          "NPN": {
            "NO": "LM5GP1DN1",
            "NC": "LM5GP1DN2"
          },
          "PNP": {
            "NO": "LM5GP1DP1",
            "NC": "LM5GP1DP2"
          },
          "检测距离": "1.0mm±10%",
          "响应频率": "2K",
          "工作电压": "10-30VDC",
          "指示灯": "黄色LED",
          "温漂": "<10%Sr",
          "负载电流": "<150mA",
          "漏电流": "<0.1mA",
          "电压降": "<1.5V",
          "电流损耗": "<10mA",
          "冲击耐压": "1000VAC  50/60Hz 60s",
          "回差": "≤15%Sr",
          "重复精度": "≤5%Sr",
          "保护": "短路保护，极性保护，浪涌保护",
          "环境温度": "-25℃～+70℃",
          "防护等级": "IP67",
          "连接方式": "2m  PVC电缆(三线）",
          "外壳材质": "不锈钢",
          "感应面材质": "PA66"
        },
        "M5_(2)": {
          "安装方式": "埋入式",
          "NPN": {
            "NO": "LM5GP1.2DN1",
            "NC": "LM5GP1.2DN2"
          },
          "PNP": {
            "NO": "LM5GP1.2DP1",
            "NC": "LM5GP1.2DP2"
          },
          "检测距离": "1.2mm±10%",
          "响应频率": "2K",
          "工作电压": "10-30VDC",
          "指示灯": "黄色LED",
          "温漂": "<10%Sr",
          "负载电流": "<150mA",
          "漏电流": "<0.1mA",
          "电压降": "<1.5V",
          "电流损耗": "<10mA",
          "冲击耐压": "1000VAC  50/60Hz 60s",
          "回差": "≤15%Sr",
          "重复精度": "≤5%Sr",
          "保护": "短路保护，极性保护，浪涌保护",
          "环境温度": "-25℃～+70℃",
          "防护等级": "IP67",
          "连接方式": "2m  PVC电缆(三线）",
          "外壳材质": "不锈钢",
          "感应面材质": "PA66"
        },
        "M5_(3)": {
          "安装方式": "埋入式",
          "NPN": {
            "NO": "LM5GP1.5DN1",
            "NC": "LM5GP1.5DN2"
          },
          "PNP": {
            "NO": "LM5GP1.5DP1",
            "NC": "LM5GP1.5DP2"
          },
          "检测距离": "1.5mm±10%",
          "响应频率": "1K",
          "工作电压": "10-30VDC",
          "指示灯": "黄色LED",
          "温漂": "<10%Sr",
          "负载电流": "<150mA",
          "漏电流": "<0.1mA",
          "电压降": "<1.5V",
          "电流损耗": "<10mA",
          "冲击耐压": "1000VAC  50/60Hz 60s",
          "回差": "≤15%Sr",
          "重复精度": "≤5%Sr",
          "保护": "短路保护，极性保护，浪涌保护",
          "环境温度": "-25℃～+70℃",
          "防护等级": "IP67",
          "连接方式": "2m  PVC电缆(三线）",
          "外壳材质": "不锈钢",
          "感应面材质": "PA66"
        },
        "Φ6.5": {
          "安装方式": "埋入式",
          "NPN": {
            "NO": "LF6.5GP1DN1",
            "NC": "LF6.5GP1DN2"
          },
          "PNP": {
            "NO": "LF6.5GP1DP1",
            "NC": "LF6.5GP1DP2"
          },
          "检测距离": "1.0mm±10%",
          "响应频率": "2K",
          "工作电压": "10-30VDC",
          "指示灯": "黄色LED",
          "温漂": "<10%Sr",
          "负载电流": "<150mA",
          "漏电流": "<0.1mA",
          "电压降": "<1.5V",
          "电流损耗": "<10mA",
          "冲击耐压": "1000VAC  50/60Hz 60s",
          "回差": "≤15%Sr",
          "重复精度": "≤5%Sr",
          "保护": "短路保护，极性保护，浪涌保护",
          "环境温度": "-25℃～+70℃",
          "防护等级": "IP67",
          "连接方式": "2m  PVC电缆(三线）",
          "外壳材质": "不锈钢",
          "感应面材质": "PA66"
        },
        "Φ6.5_(1)": {
          "安装方式": "埋入式",
          "NPN": {
            "NO": "LF6.5GP2DN1",
            "NC": "LF6.5GP2DN2"
          },
          "PNP": {
            "NO": "LF6.5GP2DP1",
            "NC": "LF6.5GP2DP2"
          },
          "检测距离": "2.0mm±10%",
          "响应频率": "1K",
          "工作电压": "10-30VDC",
          "指示灯": "黄色LED",
          "温漂": "<10%Sr",
          "负载电流": "<150mA",
          "漏电流": "<0.1mA",
          "电压降": "<1.5V",
          "电流损耗": "<10mA",
          "冲击耐压": "1000VAC  50/60Hz 60s",
          "回差": "≤15%Sr",
          "重复精度": "≤5%Sr",
          "保护": "短路保护，极性保护，浪涌保护",
          "环境温度": "-25℃～+70℃",
          "防护等级": "IP67",
          "连接方式": "2m  PVC电缆(三线）",
          "外壳材质": "不锈钢",
          "感应面材质": "PA66"
        },
        "Φ6.5_(2)": {
          "安装方式": "非埋入式",
          "NPN": {
            "NO": "LF6.5GF2DN1",
            "NC": "LF6.5GF2DN2"
          },
          "PNP": {
            "NO": "LF6.5GF2DP1",
            "NC": "LF6.5GF2DP2"
          },
          "检测距离": "2.0mm±10%",
          "响应频率": "2K",
          "工作电压": "10-30VDC",
          "指示灯": "黄色LED",
          "温漂": "<10%Sr",
          "负载电流": "<150mA",
          "漏电流": "<0.1mA",
          "电压降": "<1.5V",
          "电流损耗": "<10mA",
          "冲击耐压": "1000VAC  50/60Hz 60s",
          "回差": "≤15%Sr",
          "重复精度": "≤5%Sr",
          "保护": "短路保护，极性保护，浪涌保护",
          "环境温度": "-25℃～+70℃",
          "防护等级": "IP67",
          "连接方式": "2m  PVC电缆(三线）",
          "外壳材质": "不锈钢",
          "感应面材质": "PA66"
        }
      }
    },
    "安装尺寸": {
      "text": "",
      "img": "http://www.coolmay.com/kindeditor/attached/image/20210816/20210816114838_9137.jpg;http://www.coolmay.com/kindeditor/attached/image/20210816/20210816114901_4185.jpg;http://www.coolmay.com/kindeditor/attached/image/20210816/20210816114935_9813.jpg;"
    }
  },
  "大方型电感传感器": {
    "产品名称": "大方型电感传感器",
    "产品图片": "http://www.coolmay.com/kindeditor/attached/image/myUpload/rbmsQT202185101052.jpg",
    "产品特点": "1.方型尺寸18X18至40X40;2.感应磁性的金属物体，检测距离8-20mm;3.指示灯显示红色；4.电气接线为直流3线式连接；5.外壳防护等级为IP67;6.带短路，极性和浪涌保护功能；7.采用塑料材质；8.符合标准GB/T14048.10",
    "产品参数": {
      "型号": {
        "18X18": {
          "安装方式": "非埋入式",
          "NPN": {
            "NO": "LE18SF8DN1",
            "NC": "LE18SF8DN2"
          },
          "PNP": {
            "NO": "LE18SF8DP1",
            "NC": "LE18SF8DP2"
          },
          "检测距离": "8mm±10%",
          "响应频率": "0.8K",
          "工作电压": "10-30VDC",
          "指示灯": "红色LED",
          "温漂": "<10%Sr",
          "负载电流": "<150mA",
          "漏电流": "<0.1mA",
          "电压降": "<1.5V",
          "电流损耗": "<10mA",
          "冲击耐压": "1000VAC  50/60Hz 60s",
          "回差": "≤15%Sr",
          "重复精度": "≤3%Sr",
          "保护": "短路保护，极性，浪涌保护",
          "环境温度": "-25℃～+70℃",
          "防护等级": "IP67",
          "连接方式": "2m  PVC电缆(三线）",
          "外壳材质": "PBT",
          "感应面材质": "PBT"
        },
        "25X25": {
          "安装方式": "非埋入式",
          "NPN": {
            "NO": "LE25SF10DN1",
            "NC": "LE25SF10DN2"
          },
          "PNP": {
            "NO": "LE25SF10DP1",
            "NC": "LE25SF10DP2"
          },
          "检测距离": "10mm±10%",
          "响应频率": "0.6K",
          "工作电压": "10-30VDC",
          "指示灯": "红色LED",
          "温漂": "<10%Sr",
          "负载电流": "<150mA",
          "漏电流": "<0.1mA",
          "电压降": "<1.5V",
          "电流损耗": "<10mA",
          "冲击耐压": "1000VAC  50/60Hz 60s",
          "回差": "≤15%Sr",
          "重复精度": "≤3%Sr",
          "保护": "短路保护，极性，浪涌保护",
          "环境温度": "-25℃～+70℃",
          "防护等级": "IP67",
          "连接方式": "2m  PVC电缆(三线）",
          "外壳材质": "PBT",
          "感应面材质": "PBT"
        },
        "30X30": {
          "安装方式": "非埋入式",
          "NPN": {
            "NO": "LE30SF15DN1",
            "NC": "LE30SF15DN2"
          },
          "PNP": {
            "NO": "LE30SF15DP1",
            "NC": "LE30SF15DP2"
          },
          "检测距离": "15mm±10%",
          "响应频率": "0.4K",
          "工作电压": "10-30VDC",
          "指示灯": "红色LED",
          "温漂": "<10%Sr",
          "负载电流": "<150mA",
          "漏电流": "<0.1mA",
          "电压降": "<1.5V",
          "电流损耗": "<10mA",
          "冲击耐压": "1000VAC  50/60Hz 60s",
          "回差": "≤15%Sr",
          "重复精度": "≤3%Sr",
          "保护": "短路保护，极性，浪涌保护",
          "环境温度": "-25℃～+70℃",
          "防护等级": "IP67",
          "连接方式": "2m  PVC电缆(三线）",
          "外壳材质": "PBT",
          "感应面材质": "PBT"
        },
        "40X40": {
          "安装方式": "非埋入式",
          "NPN": {
            "NO": "LE40SF20DN1",
            "NC": "LE40SF20DN2"
          },
          "PNP": {
            "NO": "LE40SF20DP1",
            "NC": "LE40SF20DP2"
          },
          "检测距离": "20mm±10%",
          "响应频率": "0.4K",
          "工作电压": "10-30VDC",
          "指示灯": "红色LED",
          "温漂": "<10%Sr",
          "负载电流": "<150mA",
          "漏电流": "<0.1mA",
          "电压降": "<1.5V",
          "电流损耗": "<10mA",
          "冲击耐压": "1000VAC  50/60Hz 60s",
          "回差": "≤15%Sr",
          "重复精度": "≤3%Sr",
          "保护": "短路保护，极性，浪涌保护",
          "环境温度": "-25℃～+70℃",
          "防护等级": "IP67",
          "连接方式": "2m  PVC电缆(三线）",
          "外壳材质": "PBT",
          "感应面材质": "PBT"
        }
      }
    },
    "安装尺寸": {
      "text": "18X18非埋入式25X25非埋入式30X30非埋入式40X40非埋入式",
      "img": "http://www.coolmay.com/kindeditor/attached/image/20210816/20210816170705_0904.jpg;http://www.coolmay.com/kindeditor/attached/image/20210816/20210816170713_2286.jpg;http://www.coolmay.com/kindeditor/attached/image/20210816/20210816170722_9155.jpg;http://www.coolmay.com/kindeditor/attached/image/20210816/20210816170737_2691.jpg;"
    }
  },
  "距离增强圆柱型电感传感器": {
    "产品名称": "距离增强圆柱型电感传感器",
    "产品图片": "http://www.coolmay.com/kindeditor/attached/image/myUpload/m08yXa202185101113.jpg",
    "产品特点": "1.M8-M30标准圆柱型螺管;2.感应磁性的金属物体，检测距离2-22mm;检测距离比同规格标准型接近传感器远。3.指示灯显示红色；4.电气接线为直流3线式连接；5.外壳防护等级为IP67;6.带短路，极性和浪涌保护功能；7.采用铜镀镍（M8除外）；8.符合标准GB/T14048.10",
    "产品参数": {
      "型号": {
        "LM8": {
          "安装方式": "埋入式",
          "直流型": {
            "NPN": {
              "NO": "LM8GP2DD1Y",
              "NC": "LM8GP2DD2Y"
            },
            "PNP": {
              "NO": "LM8GP2DD1Y",
              "NC": "LM8GP2DD2Y"
            },
            "二线": {
              "NO": "LM8GP2DD1Y",
              "NC": "LM8GP2DD2Y"
            }
          },
          "检测距离": "2mm±10%",
          "响应频率": ">1500Hz",
          "工作电压": "10-30VDC",
          "指示灯": "红色LED",
          "温漂": "<10%Sr",
          "负载电流": "<150mA",
          "漏电流": "<0.1mA",
          "电压降": "<1.5V",
          "电流损耗": "<10mA",
          "冲击耐压": "1000VAC  50/60Hz 60s",
          "回差": "≤15%Sr",
          "重复精度": "≤3%Sr",
          "保护": "短路保护， 极性保护，浪涌保护",
          "环境温度": "-25℃～+70℃",
          "防护等级": "IP67",
          "连接方式": "2m  PVC电缆(三线）",
          "外壳材质": "LM8不锈钢，其他型号黄铜镀镍",
          "感应面材质": "PBT"
        },
        "LM8_(1)": {
          "安装方式": "非埋入式",
          "直流型": {
            "NPN": {
              "NO": "LM8GF4DD1Y",
              "NC": "LM8GF4DD2Y"
            },
            "PNP": {
              "NO": "LM8GF4DD1Y",
              "NC": "LM8GF4DD2Y"
            },
            "二线": {
              "NO": "LM8GF4DD1Y",
              "NC": "LM8GF4DD2Y"
            }
          },
          "检测距离": "4mm±10%",
          "响应频率": ">1000Hz",
          "工作电压": "10-30VDC",
          "指示灯": "红色LED",
          "温漂": "<10%Sr",
          "负载电流": "<150mA",
          "漏电流": "<0.1mA",
          "电压降": "<1.5V",
          "电流损耗": "<10mA",
          "冲击耐压": "1000VAC  50/60Hz 60s",
          "回差": "≤15%Sr",
          "重复精度": "≤3%Sr",
          "保护": "短路保护， 极性保护，浪涌保护",
          "环境温度": "-25℃～+70℃",
          "防护等级": "IP67",
          "连接方式": "2m  PVC电缆(三线）",
          "外壳材质": "LM8不锈钢，其他型号黄铜镀镍",
          "感应面材质": "PBT"
        },
        "LM12": {
          "安装方式": "埋入式",
          "直流型": {
            "NPN": {
              "NO": "LM12P4DD1Y",
              "NC": "LM12P4DD2Y"
            },
            "PNP": {
              "NO": "LM12P4DD1Y",
              "NC": "LM12P4DD2Y"
            },
            "二线": {
              "NO": "LM12P4DD1Y",
              "NC": "LM12P4DD2Y"
            }
          },
          "检测距离": "4mm±10%",
          "响应频率": ">1000Hz",
          "工作电压": "10-30VDC",
          "指示灯": "红色LED",
          "温漂": "<10%Sr",
          "负载电流": "<150mA",
          "漏电流": "<0.1mA",
          "电压降": "<1.5V",
          "电流损耗": "<10mA",
          "冲击耐压": "1000VAC  50/60Hz 60s",
          "回差": "≤15%Sr",
          "重复精度": "≤3%Sr",
          "保护": "短路保护， 极性保护，浪涌保护",
          "环境温度": "-25℃～+70℃",
          "防护等级": "IP67",
          "连接方式": "2m  PVC电缆(三线）",
          "外壳材质": "LM8不锈钢，其他型号黄铜镀镍",
          "感应面材质": "PBT"
        },
        "LM12_(1)": {
          "安装方式": "埋入式",
          "直流型": {
            "NPN": {
              "NO": "LM12P4DD1Y",
              "NC": "LM12P4DD2Y"
            },
            "PNP": {
              "NO": "LM12P4DD1Y",
              "NC": "LM12P4DD2Y"
            },
            "二线": {
              "NO": "LM12P4DD1Y",
              "NC": "LM12P4DD2Y"
            }
          },
          "检测距离": "4mm±10%",
          "响应频率": ">1000Hz",
          "工作电压": "10-30VDC",
          "指示灯": "红色LED",
          "温漂": "<10%Sr",
          "负载电流": "<150mA",
          "漏电流": "<0.1mA",
          "电压降": "<1.5V",
          "电流损耗": "<10mA",
          "冲击耐压": "1000VAC  50/60Hz 60s",
          "回差": "≤15%Sr",
          "重复精度": "≤3%Sr",
          "保护": "短路保护， 极性保护，浪涌保护",
          "环境温度": "-25℃～+70℃",
          "防护等级": "IP67",
          "连接方式": "2m  PVC电缆(三线）",
          "外壳材质": "LM8不锈钢，其他型号黄铜镀镍",
          "感应面材质": "PBT"
        },
        "LM12_(2)": {
          "安装方式": "非埋入式",
          "直流型": {
            "NPN": {
              "NO": "LM12F8DD1Y",
              "NC": "LM12F8DD2Y"
            },
            "PNP": {
              "NO": "LM12F8DD1Y",
              "NC": "LM12F8DD2Y"
            },
            "二线": {
              "NO": "LM12F8DD1Y",
              "NC": "LM12F8DD2Y"
            }
          },
          "检测距离": "8mm±10%",
          "响应频率": ">800Hz",
          "工作电压": "10-30VDC",
          "指示灯": "红色LED",
          "温漂": "<10%Sr",
          "负载电流": "<150mA",
          "漏电流": "<0.1mA",
          "电压降": "<1.5V",
          "电流损耗": "<10mA",
          "冲击耐压": "1000VAC  50/60Hz 60s",
          "回差": "≤15%Sr",
          "重复精度": "≤3%Sr",
          "保护": "短路保护， 极性保护，浪涌保护",
          "环境温度": "-25℃～+70℃",
          "防护等级": "IP67",
          "连接方式": "2m  PVC电缆(三线）",
          "外壳材质": "LM8不锈钢，其他型号黄铜镀镍",
          "感应面材质": "PBT"
        },
        "LM18": {
          "安装方式": "埋入式",
          "直流型": {
            "NPN": {
              "NO": "LM18P8DD1Y",
              "NC": "LM18P8DD2Y"
            },
            "PNP": {
              "NO": "LM18P8DD1Y",
              "NC": "LM18P8DD2Y"
            },
            "二线": {
              "NO": "LM18P8DD1Y",
              "NC": "LM18P8DD2Y"
            }
          },
          "检测距离": "8mm±10%",
          "响应频率": ">500Hz",
          "工作电压": "10-30VDC",
          "指示灯": "红色LED",
          "温漂": "<10%Sr",
          "负载电流": "<150mA",
          "漏电流": "<0.1mA",
          "电压降": "<1.5V",
          "电流损耗": "<10mA",
          "冲击耐压": "1000VAC  50/60Hz 60s",
          "回差": "≤15%Sr",
          "重复精度": "≤3%Sr",
          "保护": "短路保护， 极性保护，浪涌保护",
          "环境温度": "-25℃～+70℃",
          "防护等级": "IP67",
          "连接方式": "2m  PVC电缆(三线）",
          "外壳材质": "LM8不锈钢，其他型号黄铜镀镍",
          "感应面材质": "PBT"
        },
        "LM18_(1)": {
          "安装方式": "非埋入式",
          "直流型": {
            "NPN": {
              "NO": "LM18F12DD1Y",
              "NC": "LM18F12DD2Y"
            },
            "PNP": {
              "NO": "LM18F12DD1Y",
              "NC": "LM18F12DD2Y"
            },
            "二线": {
              "NO": "LM18F12DD1Y",
              "NC": "LM18F12DD2Y"
            }
          },
          "检测距离": "12mm±10%",
          "响应频率": ">400Hz",
          "工作电压": "10-30VDC",
          "指示灯": "红色LED",
          "温漂": "<10%Sr",
          "负载电流": "<150mA",
          "漏电流": "<0.1mA",
          "电压降": "<1.5V",
          "电流损耗": "<10mA",
          "冲击耐压": "1000VAC  50/60Hz 60s",
          "回差": "≤15%Sr",
          "重复精度": "≤3%Sr",
          "保护": "短路保护， 极性保护，浪涌保护",
          "环境温度": "-25℃～+70℃",
          "防护等级": "IP67",
          "连接方式": "2m  PVC电缆(三线）",
          "外壳材质": "LM8不锈钢，其他型号黄铜镀镍",
          "感应面材质": "PBT"
        },
        "LM30": {
          "安装方式": "埋入式",
          "直流型": {
            "NPN": {
              "NO": "LM30P15DD1Y",
              "NC": "LM30P15DD2Y"
            },
            "PNP": {
              "NO": "LM30P15DD1Y",
              "NC": "LM30P15DD2Y"
            },
            "二线": {
              "NO": "LM30P15DD1Y",
              "NC": "LM30P15DD2Y"
            }
          },
          "检测距离": "15mm±10%",
          "响应频率": ">250Hz",
          "工作电压": "10-30VDC",
          "指示灯": "红色LED",
          "温漂": "<10%Sr",
          "负载电流": "<150mA",
          "漏电流": "<0.1mA",
          "电压降": "<1.5V",
          "电流损耗": "<10mA",
          "冲击耐压": "1000VAC  50/60Hz 60s",
          "回差": "≤15%Sr",
          "重复精度": "≤3%Sr",
          "保护": "短路保护， 极性保护，浪涌保护",
          "环境温度": "-25℃～+70℃",
          "防护等级": "IP67",
          "连接方式": "2m  PVC电缆(三线）",
          "外壳材质": "LM8不锈钢，其他型号黄铜镀镍",
          "感应面材质": "PBT"
        },
        "LM30_(1)": {
          "安装方式": "非埋入式",
          "直流型": {
            "NPN": {
              "NO": "LM30F22DD1Y",
              "NC": "LM30F22DD2Y"
            },
            "PNP": {
              "NO": "LM30F22DD1Y",
              "NC": "LM30F22DD2Y"
            },
            "二线": {
              "NO": "LM30F22DD1Y",
              "NC": "LM30F22DD2Y"
            }
          },
          "检测距离": "22mm±10%",
          "响应频率": ">100Hz",
          "工作电压": "10-30VDC",
          "指示灯": "红色LED",
          "温漂": "<10%Sr",
          "负载电流": "<150mA",
          "漏电流": "<0.1mA",
          "电压降": "<1.5V",
          "电流损耗": "<10mA",
          "冲击耐压": "1000VAC  50/60Hz 60s",
          "回差": "≤15%Sr",
          "重复精度": "≤3%Sr",
          "保护": "短路保护， 极性保护，浪涌保护",
          "环境温度": "-25℃～+70℃",
          "防护等级": "IP67",
          "连接方式": "2m  PVC电缆(三线）",
          "外壳材质": "LM8不锈钢，其他型号黄铜镀镍",
          "感应面材质": "PBT"
        }
      }
    },
    "安装尺寸": {
      "text": "LM8埋入式LM8非埋入式LM12埋入式LM12非埋入式LM18埋入式LM18非埋入式LM30埋入式LM30非埋入式",
      "img": "http://www.coolmay.com/kindeditor/attached/image/20210816/20210816171353_5516.jpg;http://www.coolmay.com/kindeditor/attached/image/20210816/20210816171403_8586.jpg;http://www.coolmay.com/kindeditor/attached/image/20210816/20210816171421_4971.jpg;http://www.coolmay.com/kindeditor/attached/image/20210816/20210816171433_1292.jpg;http://www.coolmay.com/kindeditor/attached/image/20210816/20210816171456_5534.jpg;http://www.coolmay.com/kindeditor/attached/image/20210816/20210816171510_2430.jpg;http://www.coolmay.com/kindeditor/attached/image/20210816/20210816171522_5625.jpg;http://www.coolmay.com/kindeditor/attached/image/20210816/20210816171537_7627.jpg;"
    }
  },
  "小方型电感式传感器": {
    "产品名称": "小方型电感式传感器",
    "产品图片": "http://www.coolmay.com/kindeditor/attached/image/myUpload/Uq1sTo202185101136.jpg",
    "产品特点": "1.方型体积小，尺寸5X5至10X10;2.感应磁性的金属物体，检测距离1-4mm;3.指示灯显示红色；4.电气接线为直流3线式连接；5.外壳防护等级为IP67;6.带短路，极性和浪涌保护功能；7.采用塑料材质；8.符合标准GB/T14048.10",
    "产品参数": {
      "型 号": {
        "5X5": {
          "安装方式": "埋入式",
          "NPN": {
            "NO": "LE5SF1DN1",
            "NC": "LE5SF1DN2"
          },
          "PNP": {
            "NO": "LE5SF1DP1",
            "NC": "LE5SF1DP2"
          },
          "检测距离": "1.0mm±10%",
          "响应频率": "2K",
          "工作电压": "10-30VDC",
          "指示灯": "红色LED",
          "温漂": "<10%Sr",
          "负载电流": "<150mA",
          "漏电流": "<0.1mA",
          "电压降": "<1.5V",
          "电流损耗": "<10mA",
          "冲击耐压": "1000VAC  50/60Hz 60s",
          "回差": "≤15%Sr",
          "重复精度": "≤3%Sr",
          "保护": "短路保护， 极性，浪涌保护",
          "环境温度": "-25℃～+70℃",
          "防护等级": "IP67",
          "连接方式": "2m  PVC电缆(三线）",
          "感应面材质": "ABS"
        },
        "5X5_(1)": {
          "安装方式": "埋入式",
          "NPN": {
            "NO": "LE5SF1DN1",
            "NC": "LE5SF1DN2"
          },
          "PNP": {
            "NO": "LE5SF1DP1",
            "NC": "LE5SF1DP2"
          },
          "检测距离": "1.0mm±10%",
          "响应频率": "2K",
          "工作电压": "10-30VDC",
          "指示灯": "红色LED",
          "温漂": "<10%Sr",
          "负载电流": "<150mA",
          "漏电流": "<0.1mA",
          "电压降": "<1.5V",
          "电流损耗": "<10mA",
          "冲击耐压": "1000VAC  50/60Hz 60s",
          "回差": "≤15%Sr",
          "重复精度": "≤3%Sr",
          "保护": "短路保护， 极性，浪涌保护",
          "环境温度": "-25℃～+70℃",
          "防护等级": "IP67",
          "连接方式": "2m  PVC电缆(三线）",
          "感应面材质": "ABS"
        },
        "8X8": {
          "安装方式": "非埋入式",
          "NPN": {
            "NO": "LE8SF2.5DN1",
            "NC": "LE8SF2.5DN2"
          },
          "PNP": {
            "NO": "LE8SF2.5DP1",
            "NC": "LE8SF2.5DP2"
          },
          "检测距离": "2.5mm±10%",
          "响应频率": "2K",
          "工作电压": "10-30VDC",
          "指示灯": "红色LED",
          "温漂": "<10%Sr",
          "负载电流": "<150mA",
          "漏电流": "<0.1mA",
          "电压降": "<1.5V",
          "电流损耗": "<10mA",
          "冲击耐压": "1000VAC  50/60Hz 60s",
          "回差": "≤15%Sr",
          "重复精度": "≤3%Sr",
          "保护": "短路保护， 极性，浪涌保护",
          "环境温度": "-25℃～+70℃",
          "防护等级": "IP67",
          "连接方式": "2m  PVC电缆(三线）",
          "感应面材质": "PC"
        },
        "8X8_(1)": {
          "安装方式": "非埋入式",
          "NPN": {
            "NO": "LE8SF2.5DN1",
            "NC": "LE8SF2.5DN2"
          },
          "PNP": {
            "NO": "LE8SF2.5DP1",
            "NC": "LE8SF2.5DP2"
          },
          "检测距离": "2.5mm±10%",
          "响应频率": "2K",
          "工作电压": "10-30VDC",
          "指示灯": "红色LED",
          "温漂": "<10%Sr",
          "负载电流": "<150mA",
          "漏电流": "<0.1mA",
          "电压降": "<1.5V",
          "电流损耗": "<10mA",
          "冲击耐压": "1000VAC  50/60Hz 60s",
          "回差": "≤15%Sr",
          "重复精度": "≤3%Sr",
          "保护": "短路保护， 极性，浪涌保护",
          "环境温度": "-25℃～+70℃",
          "防护等级": "IP67",
          "连接方式": "2m  PVC电缆(三线）",
          "感应面材质": "PC"
        },
        "8X8_(2)": {
          "安装方式": "非埋入式",
          "NPN": {
            "NO": "LE8SF2.5DN1-A",
            "NC": "LE8SF2.5DN2-A"
          },
          "PNP": {
            "NO": "LE8SF2.5DP1-A",
            "NC": "LE8SF2.5DP2-A"
          },
          "检测距离": "2.5mm±10%",
          "响应频率": "2K",
          "工作电压": "10-30VDC",
          "指示灯": "红色LED",
          "温漂": "<10%Sr",
          "负载电流": "<150mA",
          "漏电流": "<0.1mA",
          "电压降": "<1.5V",
          "电流损耗": "<10mA",
          "冲击耐压": "1000VAC  50/60Hz 60s",
          "回差": "≤15%Sr",
          "重复精度": "≤3%Sr",
          "保护": "短路保护， 极性，浪涌保护",
          "环境温度": "-25℃～+70℃",
          "防护等级": "IP67",
          "连接方式": "2m  PVC电缆(三线）",
          "感应面材质": "AAS"
        },
        "8X8_(3)": {
          "安装方式": "非埋入式",
          "NPN": {
            "NO": "LE8SF2.5DN1-A",
            "NC": "LE8SF2.5DN2-A"
          },
          "PNP": {
            "NO": "LE8SF2.5DP1-A",
            "NC": "LE8SF2.5DP2-A"
          },
          "检测距离": "2.5mm±10%",
          "响应频率": "2K",
          "工作电压": "10-30VDC",
          "指示灯": "红色LED",
          "温漂": "<10%Sr",
          "负载电流": "<150mA",
          "漏电流": "<0.1mA",
          "电压降": "<1.5V",
          "电流损耗": "<10mA",
          "冲击耐压": "1000VAC  50/60Hz 60s",
          "回差": "≤15%Sr",
          "重复精度": "≤3%Sr",
          "保护": "短路保护， 极性，浪涌保护",
          "环境温度": "-25℃～+70℃",
          "防护等级": "IP67",
          "连接方式": "2m  PVC电缆(三线）",
          "感应面材质": "AAS"
        },
        "10X10": {
          "安装方式": "埋入式",
          "NPN": {
            "NO": "LE10SF2.5DN1",
            "NC": "LE10SF2.5DN2"
          },
          "PNP": {
            "NO": "LE10SF2.5DP1",
            "NC": "LE10SF2.5DP2"
          },
          "检测距离": "2.5mm±10%",
          "响应频率": "2K",
          "工作电压": "10-30VDC",
          "指示灯": "红色LED",
          "温漂": "<10%Sr",
          "负载电流": "<150mA",
          "漏电流": "<0.1mA",
          "电压降": "<1.5V",
          "电流损耗": "<10mA",
          "冲击耐压": "1000VAC  50/60Hz 60s",
          "回差": "≤15%Sr",
          "重复精度": "≤3%Sr",
          "保护": "短路保护， 极性，浪涌保护",
          "环境温度": "-25℃～+70℃",
          "防护等级": "IP67",
          "连接方式": "2m  PVC电缆(三线）",
          "感应面材质": "PBT"
        },
        "10X10_(1)": {
          "安装方式": "埋入式",
          "NPN": {
            "NO": "LE10SF2.5DN1",
            "NC": "LE10SF2.5DN2"
          },
          "PNP": {
            "NO": "LE10SF2.5DP1",
            "NC": "LE10SF2.5DP2"
          },
          "检测距离": "2.5mm±10%",
          "响应频率": "2K",
          "工作电压": "10-30VDC",
          "指示灯": "红色LED",
          "温漂": "<10%Sr",
          "负载电流": "<150mA",
          "漏电流": "<0.1mA",
          "电压降": "<1.5V",
          "电流损耗": "<10mA",
          "冲击耐压": "1000VAC  50/60Hz 60s",
          "回差": "≤15%Sr",
          "重复精度": "≤3%Sr",
          "保护": "短路保护， 极性，浪涌保护",
          "环境温度": "-25℃～+70℃",
          "防护等级": "IP67",
          "连接方式": "2m  PVC电缆(三线）",
          "感应面材质": "PBT"
        },
        "10X10_(2)": {
          "安装方式": "非埋入式",
          "NPN": {
            "NO": "LE10SF4DN1",
            "NC": "LE10SF4DN2"
          },
          "PNP": {
            "NO": "LE10SF4DP1",
            "NC": "LE10SF4DP2"
          },
          "检测距离": "4.0±10%",
          "响应频率": "2K",
          "工作电压": "10-30VDC",
          "指示灯": "红色LED",
          "温漂": "<10%Sr",
          "负载电流": "<150mA",
          "漏电流": "<0.1mA",
          "电压降": "<1.5V",
          "电流损耗": "<10mA",
          "冲击耐压": "1000VAC  50/60Hz 60s",
          "回差": "≤15%Sr",
          "重复精度": "≤3%Sr",
          "保护": "短路保护， 极性，浪涌保护",
          "环境温度": "-25℃～+70℃",
          "防护等级": "IP67",
          "连接方式": "2m  PVC电缆(三线）",
          "感应面材质": "PBT"
        },
        "10X10_(3)": {
          "安装方式": "非埋入式",
          "NPN": {
            "NO": "LE10SF4DN1",
            "NC": "LE10SF4DN2"
          },
          "PNP": {
            "NO": "LE10SF4DP1",
            "NC": "LE10SF4DP2"
          },
          "检测距离": "4.0±10%",
          "响应频率": "2K",
          "工作电压": "10-30VDC",
          "指示灯": "红色LED",
          "温漂": "<10%Sr",
          "负载电流": "<150mA",
          "漏电流": "<0.1mA",
          "电压降": "<1.5V",
          "电流损耗": "<10mA",
          "冲击耐压": "1000VAC  50/60Hz 60s",
          "回差": "≤15%Sr",
          "重复精度": "≤3%Sr",
          "保护": "短路保护， 极性，浪涌保护",
          "环境温度": "-25℃～+70℃",
          "防护等级": "IP67",
          "连接方式": "2m  PVC电缆(三线）",
          "感应面材质": "PBT"
        }
      }
    },
    "安装尺寸": {
      "text": "5X58X810X10",
      "img": "http://www.coolmay.com/kindeditor/attached/image/20210816/20210816172245_5537.jpg;http://www.coolmay.com/kindeditor/attached/image/20210816/20210816172252_7593.jpg;http://www.coolmay.com/kindeditor/attached/image/20210816/20210816172319_3299.jpg;"
    }
  },
  "圆柱型电容式接近传感器": {
    "产品名称": "圆柱型电容式接近传感器",
    "产品图片": "http://www.coolmay.com/kindeditor/attached/image/myUpload/u37tj0202185101258.jpg",
    "产品特点": "1.标准圆柱型M12-M30；2.采用电场原理，感应所有有介电常数的金属与非金属物体介电常数越大，感应距离越长；3.对检测物的范围广，金属与非金属物体都可以被感应,从2-15mm;4.指示灯黄色；5.电气接线为直流3线式连接；6.外壳防护等级为IP67;7.带短路，极性和浪涌保护功能(交流型除外)；9.壳采用ABS材质；10.符合标准GB/T14048.10",
    "产品参数": {
      "型 号": {
        "CM12": {
          "安装方式": "非埋入式",
          "直流型": {
            "NPN": {
              "NO": "CM12SF2DP1",
              "NC": "CM12SF2DP2"
            },
            "PNP": {
              "NO": "CM12SF2DP1",
              "NC": "CM12SF2DP2"
            }
          },
          "交流型": {
            "二线": {
              "NO": "CM12SF2BA1",
              "NC": "CM12SF2BA2"
            }
          },
          "检测距离": "2mm±10%",
          "响应频率": ">100Hz(交流型10Hz)",
          "工作电压": "10-30VDC,交流型AC90-250V",
          "温漂": "<10%Sr",
          "负载电流": "<150mA",
          "漏电流": "<0.1mA",
          "电压降": "<1.5V",
          "电流损耗": "<10mA",
          "回差范围": "≤15%Sr",
          "重复精度": "≤5%Sr",
          "指示灯": "红色LED",
          "保护": "极性保护，浪涌保护,短路保护，交流型除外",
          "环境温度": "-25℃～+70℃",
          "防护等级": "IP67",
          "连接方式": "2m  PVC电缆(二线，三线）",
          "外壳材质": "ABS",
          "感应面材质": "ABS"
        },
        "CM18": {
          "安装方式": "非埋入式",
          "直流型": {
            "NPN": {
              "NO": "CM18SF8DP1",
              "NC": "CM18SF8DP2"
            },
            "PNP": {
              "NO": "CM18SF8DP1",
              "NC": "CM18SF8DP2"
            }
          },
          "交流型": {
            "二线": {
              "NO": "CM18SF8BA1",
              "NC": "CM18SF8BA2"
            }
          },
          "检测距离": "8mm±10%",
          "响应频率": ">100Hz(交流型10Hz)",
          "工作电压": "10-30VDC,交流型AC90-250V",
          "温漂": "<10%Sr",
          "负载电流": "<150mA",
          "漏电流": "<0.1mA",
          "电压降": "<1.5V",
          "电流损耗": "<10mA",
          "回差范围": "≤15%Sr",
          "重复精度": "≤5%Sr",
          "指示灯": "红色LED",
          "保护": "极性保护，浪涌保护,短路保护，交流型除外",
          "环境温度": "-25℃～+70℃",
          "防护等级": "IP67",
          "连接方式": "2m  PVC电缆(二线，三线）",
          "外壳材质": "ABS",
          "感应面材质": "ABS"
        },
        "CM30": {
          "安装方式": "非埋入式",
          "直流型": {
            "NPN": {
              "NO": "CM30SF15DP1",
              "NC": "CM30SF15DP2"
            },
            "PNP": {
              "NO": "CM30SF15DP1",
              "NC": "CM30SF15DP2"
            }
          },
          "交流型": {
            "二线": {
              "NO": "CM30SF15BA1",
              "NC": "CM30SF15BA2"
            }
          },
          "检测距离": "15mm±10%",
          "响应频率": ">100Hz(交流型10Hz)",
          "工作电压": "10-30VDC,交流型AC90-250V",
          "温漂": "<10%Sr",
          "负载电流": "<150mA",
          "漏电流": "<0.1mA",
          "电压降": "<1.5V",
          "电流损耗": "<10mA",
          "回差范围": "≤15%Sr",
          "重复精度": "≤5%Sr",
          "指示灯": "红色LED",
          "保护": "极性保护，浪涌保护,短路保护，交流型除外",
          "环境温度": "-25℃～+70℃",
          "防护等级": "IP67",
          "连接方式": "2m  PVC电缆(二线，三线）",
          "外壳材质": "ABS",
          "感应面材质": "ABS"
        }
      }
    },
    "安装尺寸": {
      "text": "CM12         CM18CM30",
      "img": "http://www.coolmay.com/kindeditor/attached/image/20210816/20210816173038_0391.jpg;http://www.coolmay.com/kindeditor/attached/image/20210816/20210816173049_5862.jpg;http://www.coolmay.com/kindeditor/attached/image/20210816/20210816173123_1299.jpg;"
    }
  },
  "标准圆柱型光电传感器": {
    "产品名称": "标准圆柱型光电传感器",
    "产品图片": "http://www.coolmay.com/kindeditor/attached/image/myUpload/ptzImq202185101327.jpg",
    "产品特点": "1.标准型直径M12-M18；2.对检测物的范围广，金属与非金属物体都可以被感应，感应距离长，从200mm-15m;3.漫反射型产品可针对安装现场对感应距离进行一定范围的调整；4.指示灯黄色；5.电气接线为直流3线式连接；6.外壳防护等级为IP67;7.带短路，极性和浪涌保护功能；8.壳采用黄铜镀镍；9.符合标准GB/T14048.10",
    "产品参数": {
      "型 号": {
        "GM12T": {
          "模式": "对射",
          "直流型": {
            "NPN": {
              "NO": "GM12T5000DP1",
              "NC": "GM12T5000DP2"
            },
            "PNP": {
              "NO": "GM12T5000DP1",
              "NC": "GM12T5000DP2"
            }
          },
          "检测距离": "5m",
          "感应物大小": "》Φ8mm",
          "工作电压": "10-30VDC",
          "光源": "不可见红外光（880nm）",
          "温漂": "<10%Sr",
          "负载电流": "<200mA",
          "漏电流": "<0.1mA",
          "电压降": "<2.5V",
          "电流损耗": "<30mA",
          "冲击耐压": "1000VAC  50/60Hz 60s",
          "响应时间": "≤5ms",
          "重复精度": "≤5%Sr",
          "指示灯": "黄色LED",
          "保护": "极性保护，浪涌保护,短路保护",
          "环境温度": "-5℃～+55℃（35 to 85% RH）",
          "防护等级": "IP67",
          "连接方式": "2m  PVC电缆(三线）",
          "外壳材质": "黄铜镀镍",
          "感应面材质": "滤光镜片"
        },
        "GM12D": {
          "模式": "漫反射",
          "直流型": {
            "NPN": {
              "NO": "GM12D200DP1",
              "NC": "GM12D200DP2"
            },
            "PNP": {
              "NO": "GM12D200DP1",
              "NC": "GM12D200DP2"
            }
          },
          "检测距离": "200mm内可调",
          "感应物大小": "10  *10cm白纸板",
          "工作电压": "10-30VDC",
          "光源": "不可见红外光（880nm）",
          "温漂": "<10%Sr",
          "负载电流": "<200mA",
          "漏电流": "<0.1mA",
          "电压降": "<2.5V",
          "电流损耗": "<30mA",
          "冲击耐压": "1000VAC  50/60Hz 60s",
          "响应时间": "≤5ms",
          "重复精度": "≤5%Sr",
          "指示灯": "黄色LED",
          "保护": "极性保护，浪涌保护,短路保护",
          "环境温度": "-5℃～+55℃（35 to 85% RH）",
          "防护等级": "IP67",
          "连接方式": "2m  PVC电缆(三线）",
          "外壳材质": "黄铜镀镍",
          "感应面材质": "滤光镜片"
        },
        "GM12D_(1)": {
          "模式": "漫反射",
          "直流型": {
            "NPN": {
              "NO": "GM12D300DP1",
              "NC": "GM12D300DP2"
            },
            "PNP": {
              "NO": "GM12D300DP1",
              "NC": "GM12D300DP2"
            }
          },
          "检测距离": "300mm内可调",
          "感应物大小": "10  *10cm白纸板",
          "工作电压": "10-30VDC",
          "光源": "不可见红外光（880nm）",
          "温漂": "<10%Sr",
          "负载电流": "<200mA",
          "漏电流": "<0.1mA",
          "电压降": "<2.5V",
          "电流损耗": "<30mA",
          "冲击耐压": "1000VAC  50/60Hz 60s",
          "响应时间": "≤5ms",
          "重复精度": "≤5%Sr",
          "指示灯": "黄色LED",
          "保护": "极性保护，浪涌保护,短路保护",
          "环境温度": "-5℃～+55℃（35 to 85% RH）",
          "防护等级": "IP67",
          "连接方式": "2m  PVC电缆(三线）",
          "外壳材质": "黄铜镀镍",
          "感应面材质": "滤光镜片"
        },
        "GM18T": {
          "模式": "对射",
          "直流型": {
            "NPN": {
              "NO": "GM18T15000DP1",
              "NC": "GM18T15000DP2"
            },
            "PNP": {
              "NO": "GM18T15000DP1",
              "NC": "GM18T15000DP2"
            }
          },
          "检测距离": "15m",
          "感应物大小": "》Φ8mm",
          "工作电压": "10-30VDC",
          "光源": "不可见红外光（880nm）",
          "温漂": "<10%Sr",
          "负载电流": "<200mA",
          "漏电流": "<0.1mA",
          "电压降": "<2.5V",
          "电流损耗": "<30mA",
          "冲击耐压": "1000VAC  50/60Hz 60s",
          "响应时间": "≤5ms",
          "重复精度": "≤5%Sr",
          "指示灯": "黄色LED",
          "保护": "极性保护，浪涌保护,短路保护",
          "环境温度": "-5℃～+55℃（35 to 85% RH）",
          "防护等级": "IP67",
          "连接方式": "2m  PVC电缆(三线）",
          "外壳材质": "黄铜镀镍",
          "感应面材质": "滤光镜片"
        },
        "GM18D": {
          "模式": "漫反射",
          "直流型": {
            "NPN": {
              "NO": "GM18D300DP1",
              "NC": "GM18D300DP2"
            },
            "PNP": {
              "NO": "GM18D300DP1",
              "NC": "GM18D300DP2"
            }
          },
          "检测距离": "300mm内可调",
          "感应物大小": "10  *10cm白纸板",
          "工作电压": "10-30VDC",
          "光源": "不可见红外光（880nm）",
          "温漂": "<10%Sr",
          "负载电流": "<200mA",
          "漏电流": "<0.1mA",
          "电压降": "<2.5V",
          "电流损耗": "<30mA",
          "冲击耐压": "1000VAC  50/60Hz 60s",
          "响应时间": "≤5ms",
          "重复精度": "≤5%Sr",
          "指示灯": "黄色LED",
          "保护": "极性保护，浪涌保护,短路保护",
          "环境温度": "-5℃～+55℃（35 to 85% RH）",
          "防护等级": "IP67",
          "连接方式": "2m  PVC电缆(三线）",
          "外壳材质": "黄铜镀镍",
          "感应面材质": "滤光镜片"
        },
        "GM18D_(1)": {
          "模式": "漫反射",
          "直流型": {
            "NPN": {
              "NO": "GM18D500DP1",
              "NC": "GM18D500DP2"
            },
            "PNP": {
              "NO": "GM18D500DP1",
              "NC": "GM18D500DP2"
            }
          },
          "检测距离": "500mm内可调",
          "感应物大小": "10  *10cm白纸板",
          "工作电压": "10-30VDC",
          "光源": "不可见红外光（880nm）",
          "温漂": "<10%Sr",
          "负载电流": "<200mA",
          "漏电流": "<0.1mA",
          "电压降": "<2.5V",
          "电流损耗": "<30mA",
          "冲击耐压": "1000VAC  50/60Hz 60s",
          "响应时间": "≤5ms",
          "重复精度": "≤5%Sr",
          "指示灯": "黄色LED",
          "保护": "极性保护，浪涌保护,短路保护",
          "环境温度": "-5℃～+55℃（35 to 85% RH）",
          "防护等级": "IP67",
          "连接方式": "2m  PVC电缆(三线）",
          "外壳材质": "黄铜镀镍",
          "感应面材质": "滤光镜片"
        },
        "GM18D_(2)": {
          "模式": "漫反射",
          "直流型": {
            "NPN": {
              "NO": "GM18D1000DP1",
              "NC": "GM18D1000DP2"
            },
            "PNP": {
              "NO": "GM18D1000DP1",
              "NC": "GM18D1000DP2"
            }
          },
          "检测距离": "1m内可调",
          "感应物大小": "10  *10cm白纸板",
          "工作电压": "10-30VDC",
          "光源": "不可见红外光（880nm）",
          "温漂": "<10%Sr",
          "负载电流": "<200mA",
          "漏电流": "<0.1mA",
          "电压降": "<2.5V",
          "电流损耗": "<30mA",
          "冲击耐压": "1000VAC  50/60Hz 60s",
          "响应时间": "≤5ms",
          "重复精度": "≤5%Sr",
          "指示灯": "黄色LED",
          "保护": "极性保护，浪涌保护,短路保护",
          "环境温度": "-5℃～+55℃（35 to 85% RH）",
          "防护等级": "IP67",
          "连接方式": "2m  PVC电缆(三线）",
          "外壳材质": "黄铜镀镍",
          "感应面材质": "滤光镜片"
        }
      }
    },
    "安装尺寸": {
      "text": "GM12T对射GM12D漫反射GM18T对射GM18D漫反射",
      "img": "http://www.coolmay.com/kindeditor/attached/image/20210816/20210816180150_3742.jpg;http://www.coolmay.com/kindeditor/attached/image/20210816/20210816180156_2973.jpg;http://www.coolmay.com/kindeditor/attached/image/20210816/20210816180203_7624.jpg;http://www.coolmay.com/kindeditor/attached/image/20210816/20210816180214_8009.jpg;"
    }
  },
  "超细圆柱光电传感器": {
    "产品名称": "超细圆柱光电传感器",
    "产品图片": "http://www.coolmay.com/kindeditor/attached/image/myUpload/uoUvt8202185101540.jpg",
    "产品特点": "1.超细，直径从M3-M6不等，使用空间小；2.对检测物的范围广，金属与非金属物体都可以被感应，感应距离长，从30-200mm;3.产品可针对安装现场对感应距离进行一定范围的调整；4.指示灯黄色；5.电气接线为直流3线式连接；6.外壳防护等级为IP67;7.带短路，极性和浪涌保护功能；8.采用不锈钢材质；9.符合标准GB/T14048.10",
    "产品参数": {
      "型 号": {
        "GM3": {
          "模式": "漫反射",
          "直流型": {
            "NPN": {
              "NO": "GM3GD30DP1",
              "NC": "GM3GD30DP2"
            },
            "PNP": {
              "NO": "GM3GD30DP1",
              "NC": "GM3GD30DP2"
            }
          },
          "检测距离": "30mm内可调",
          "响应频率": ">100Hz",
          "工作电压": "10-30VDC",
          "光源": "不可见红外光（880nm）",
          "温漂": "<10%Sr",
          "负载电流": "<150mA",
          "漏电流": "<0.1mA",
          "电压降": "<1.5V",
          "电流损耗": "<10mA",
          "冲击耐压": "1000VAC  50/60Hz 60s",
          "回差": "≤15%Sr",
          "重复精度": "≤3%Sr",
          "指示灯": "黄色LED",
          "保护": "极性保护，浪涌保护,短路保护",
          "环境温度": "-5℃～+55℃",
          "防护等级": "IP67",
          "连接方式": "2m  PVC电缆(三线）",
          "外壳材质": "不锈钢",
          "感应面材质": "滤光镜片"
        },
        "GM3_(1)": {
          "模式": "漫反射",
          "直流型": {
            "NPN": {
              "NO": "GM3GD40DP1",
              "NC": "GM3GD40DP2"
            },
            "PNP": {
              "NO": "GM3GD40DP1",
              "NC": "GM3GD40DP2"
            }
          },
          "检测距离": "40mm内可调",
          "响应频率": ">100Hz",
          "工作电压": "10-30VDC",
          "光源": "不可见红外光（880nm）",
          "温漂": "<10%Sr",
          "负载电流": "<150mA",
          "漏电流": "<0.1mA",
          "电压降": "<1.5V",
          "电流损耗": "<10mA",
          "冲击耐压": "1000VAC  50/60Hz 60s",
          "回差": "≤15%Sr",
          "重复精度": "≤3%Sr",
          "指示灯": "黄色LED",
          "保护": "极性保护，浪涌保护,短路保护",
          "环境温度": "-5℃～+55℃",
          "防护等级": "IP67",
          "连接方式": "2m  PVC电缆(三线）",
          "外壳材质": "不锈钢",
          "感应面材质": "滤光镜片"
        },
        "GM4": {
          "模式": "漫反射",
          "直流型": {
            "NPN": {
              "NO": "GM4GD50DP1",
              "NC": "GM4GD50DP2"
            },
            "PNP": {
              "NO": "GM4GD50DP1",
              "NC": "GM4GD50DP2"
            }
          },
          "检测距离": "50mm内可调",
          "响应频率": ">100Hz",
          "工作电压": "10-30VDC",
          "光源": "不可见红外光（880nm）",
          "温漂": "<10%Sr",
          "负载电流": "<150mA",
          "漏电流": "<0.1mA",
          "电压降": "<1.5V",
          "电流损耗": "<10mA",
          "冲击耐压": "1000VAC  50/60Hz 60s",
          "回差": "≤15%Sr",
          "重复精度": "≤3%Sr",
          "指示灯": "黄色LED",
          "保护": "极性保护，浪涌保护,短路保护",
          "环境温度": "-5℃～+55℃",
          "防护等级": "IP67",
          "连接方式": "2m  PVC电缆(三线）",
          "外壳材质": "不锈钢",
          "感应面材质": "滤光镜片"
        },
        "GM4_(1)": {
          "模式": "漫反射",
          "直流型": {
            "NPN": {
              "NO": "GM4GD70DP1",
              "NC": "GM4GD70DP2"
            },
            "PNP": {
              "NO": "GM4GD70DP1",
              "NC": "GM4GD70DP2"
            }
          },
          "检测距离": "70mm内可调",
          "响应频率": ">100Hz",
          "工作电压": "10-30VDC",
          "光源": "不可见红外光（880nm）",
          "温漂": "<10%Sr",
          "负载电流": "<150mA",
          "漏电流": "<0.1mA",
          "电压降": "<1.5V",
          "电流损耗": "<10mA",
          "冲击耐压": "1000VAC  50/60Hz 60s",
          "回差": "≤15%Sr",
          "重复精度": "≤3%Sr",
          "指示灯": "黄色LED",
          "保护": "极性保护，浪涌保护,短路保护",
          "环境温度": "-5℃～+55℃",
          "防护等级": "IP67",
          "连接方式": "2m  PVC电缆(三线）",
          "外壳材质": "不锈钢",
          "感应面材质": "滤光镜片"
        },
        "GM5": {
          "模式": "漫反射",
          "直流型": {
            "NPN": {
              "NO": "GM5GD100DP1",
              "NC": "GM5GD100DP2"
            },
            "PNP": {
              "NO": "GM5GD100DP1",
              "NC": "GM5GD100DP2"
            }
          },
          "检测距离": "100mm内可调",
          "响应频率": ">100Hz",
          "工作电压": "10-30VDC",
          "光源": "不可见红外光（880nm）",
          "温漂": "<10%Sr",
          "负载电流": "<150mA",
          "漏电流": "<0.1mA",
          "电压降": "<1.5V",
          "电流损耗": "<10mA",
          "冲击耐压": "1000VAC  50/60Hz 60s",
          "回差": "≤15%Sr",
          "重复精度": "≤3%Sr",
          "指示灯": "黄色LED",
          "保护": "极性保护，浪涌保护,短路保护",
          "环境温度": "-5℃～+55℃",
          "防护等级": "IP67",
          "连接方式": "2m  PVC电缆(三线）",
          "外壳材质": "不锈钢",
          "感应面材质": "滤光镜片"
        },
        "GM5_(1)": {
          "模式": "漫反射",
          "直流型": {
            "NPN": {
              "NO": "GM5GD130DP1",
              "NC": "GM5GD130DP2"
            },
            "PNP": {
              "NO": "GM5GD130DP1",
              "NC": "GM5GD130DP2"
            }
          },
          "检测距离": "130mm内可调",
          "响应频率": ">100Hz",
          "工作电压": "10-30VDC",
          "光源": "不可见红外光（880nm）",
          "温漂": "<10%Sr",
          "负载电流": "<150mA",
          "漏电流": "<0.1mA",
          "电压降": "<1.5V",
          "电流损耗": "<10mA",
          "冲击耐压": "1000VAC  50/60Hz 60s",
          "回差": "≤15%Sr",
          "重复精度": "≤3%Sr",
          "指示灯": "黄色LED",
          "保护": "极性保护，浪涌保护,短路保护",
          "环境温度": "-5℃～+55℃",
          "防护等级": "IP67",
          "连接方式": "2m  PVC电缆(三线）",
          "外壳材质": "不锈钢",
          "感应面材质": "滤光镜片"
        },
        "GM6": {
          "模式": "漫反射",
          "直流型": {
            "NPN": {
              "NO": "GM6GD150DP1",
              "NC": "GM6GD150DP2"
            },
            "PNP": {
              "NO": "GM6GD150DP1",
              "NC": "GM6GD150DP2"
            }
          },
          "检测距离": "150mm内可调",
          "响应频率": ">100Hz",
          "工作电压": "10-30VDC",
          "光源": "不可见红外光（880nm）",
          "温漂": "<10%Sr",
          "负载电流": "<150mA",
          "漏电流": "<0.1mA",
          "电压降": "<1.5V",
          "电流损耗": "<10mA",
          "冲击耐压": "1000VAC  50/60Hz 60s",
          "回差": "≤15%Sr",
          "重复精度": "≤3%Sr",
          "指示灯": "黄色LED",
          "保护": "极性保护，浪涌保护,短路保护",
          "环境温度": "-5℃～+55℃",
          "防护等级": "IP67",
          "连接方式": "2m  PVC电缆(三线）",
          "外壳材质": "不锈钢",
          "感应面材质": "滤光镜片"
        },
        "GM6_(1)": {
          "模式": "漫反射",
          "直流型": {
            "NPN": {
              "NO": "GM6GD200DP1",
              "NC": "GM6GD200DP2"
            },
            "PNP": {
              "NO": "GM6GD200DP1",
              "NC": "GM6GD200DP2"
            }
          },
          "检测距离": "200mm内可调",
          "响应频率": ">100Hz",
          "工作电压": "10-30VDC",
          "光源": "不可见红外光（880nm）",
          "温漂": "<10%Sr",
          "负载电流": "<150mA",
          "漏电流": "<0.1mA",
          "电压降": "<1.5V",
          "电流损耗": "<10mA",
          "冲击耐压": "1000VAC  50/60Hz 60s",
          "回差": "≤15%Sr",
          "重复精度": "≤3%Sr",
          "指示灯": "黄色LED",
          "保护": "极性保护，浪涌保护,短路保护",
          "环境温度": "-5℃～+55℃",
          "防护等级": "IP67",
          "连接方式": "2m  PVC电缆(三线）",
          "外壳材质": "不锈钢",
          "感应面材质": "滤光镜片"
        }
      }
    },
    "安装尺寸": {
      "text": "GM3漫反射GM4漫反射GM5漫反射GM6漫反射",
      "img": "http://www.coolmay.com/kindeditor/attached/image/20210817/20210817090335_6851.jpg;http://www.coolmay.com/kindeditor/attached/image/20210817/20210817090349_6364.jpg;http://www.coolmay.com/kindeditor/attached/image/20210817/20210817090359_2168.jpg;http://www.coolmay.com/kindeditor/attached/image/20210817/20210817090409_1498.jpg;"
    }
  },
  "方型光电传感器": {
    "产品名称": "方型光电传感器",
    "产品图片": "http://www.coolmay.com/kindeditor/attached/image/myUpload/pCH2sN202185101409.jpg",
    "产品特点": "1.方型美观，结构紧凑；2.对检测物的范围广，金属与非金属物体都可以被感应，感应距离长，从100-300mm,对射距离可达5m;3.漫反射型产品可针对安装现场对感应距离进行一定范围的调整；4.指示灯黄色；5.电气接线为直流3线式连接；6.外壳防护等级为IP67;7.带短路，极性和浪涌保护功能；8.壳采用黄铜镀镍；9.符合标准GB/T14048.10",
    "产品参数": {
      "型 号": {
        "GE31ST": {
          "模式": "对射",
          "直流型": {
            "NPN": {
              "NO": "GE31ST5000DP1",
              "NC": "GE31ST5000DP2"
            },
            "PNP": {
              "NO": "GE31ST5000DP1",
              "NC": "GE31ST5000DP2"
            }
          },
          "检测距离": "5m",
          "感应物大小": "≥Φ8",
          "工作电压": "10-30VDC",
          "光源": "不可见红外光（880nm）",
          "温漂": "<10%Sr",
          "负载电流": "<200mA",
          "漏电流": "<0.1mA",
          "电压降": "<2.5V",
          "电流损耗": "<30mA",
          "冲击耐压": "1000VAC  50/60Hz 60s",
          "响应时间": "≤5ms",
          "重复精度": "≤5%Sr",
          "指示灯": "黄色LED",
          "保护": "极性保护，浪涌保护,短路保护",
          "环境温度": "-5℃～+55℃(35 to 85% RH)",
          "防护等级": "IP55",
          "连接方式": "2m  PVC电缆(三线）",
          "外壳材质": "ABS",
          "感应面材质": "滤光镜片"
        },
        "GE31SD": {
          "模式": "漫反射",
          "直流型": {
            "NPN": {
              "NO": "GE31SD100DP1",
              "NC": "GE31SD100DP2"
            },
            "PNP": {
              "NO": "GE31SD100DP1",
              "NC": "GE31SD100DP2"
            }
          },
          "检测距离": "100mm可调",
          "感应物大小": "10 *10cm白纸板",
          "工作电压": "10-30VDC",
          "光源": "不可见红外光（880nm）",
          "温漂": "<10%Sr",
          "负载电流": "<200mA",
          "漏电流": "<0.1mA",
          "电压降": "<2.5V",
          "电流损耗": "<30mA",
          "冲击耐压": "1000VAC  50/60Hz 60s",
          "响应时间": "≤5ms",
          "重复精度": "≤5%Sr",
          "指示灯": "黄色LED",
          "保护": "极性保护，浪涌保护,短路保护",
          "环境温度": "-5℃～+55℃(35 to 85% RH)",
          "防护等级": "IP55",
          "连接方式": "2m  PVC电缆(三线）",
          "外壳材质": "ABS",
          "感应面材质": "滤光镜片"
        },
        "GE31SD_(1)": {
          "模式": "漫反射",
          "直流型": {
            "NPN": {
              "NO": "GE31SD200DP1",
              "NC": "GE31SD200DP2"
            },
            "PNP": {
              "NO": "GE31SD200DP1",
              "NC": "GE31SD200DP2"
            }
          },
          "检测距离": "200mm可调",
          "感应物大小": "10 *10cm白纸板",
          "工作电压": "10-30VDC",
          "光源": "不可见红外光（880nm）",
          "温漂": "<10%Sr",
          "负载电流": "<200mA",
          "漏电流": "<0.1mA",
          "电压降": "<2.5V",
          "电流损耗": "<30mA",
          "冲击耐压": "1000VAC  50/60Hz 60s",
          "响应时间": "≤5ms",
          "重复精度": "≤5%Sr",
          "指示灯": "黄色LED",
          "保护": "极性保护，浪涌保护,短路保护",
          "环境温度": "-5℃～+55℃(35 to 85% RH)",
          "防护等级": "IP55",
          "连接方式": "2m  PVC电缆(三线）",
          "外壳材质": "ABS",
          "感应面材质": "滤光镜片"
        },
        "GE31SD_(2)": {
          "模式": "漫反射",
          "直流型": {
            "NPN": {
              "NO": "GE31SD300DP1",
              "NC": "GE31SD300DP2"
            },
            "PNP": {
              "NO": "GE31SD300DP1",
              "NC": "GE31SD300DP2"
            }
          },
          "检测距离": "300mm可调",
          "感应物大小": "10 *10cm白纸板",
          "工作电压": "10-30VDC",
          "光源": "不可见红外光（880nm）",
          "温漂": "<10%Sr",
          "负载电流": "<200mA",
          "漏电流": "<0.1mA",
          "电压降": "<2.5V",
          "电流损耗": "<30mA",
          "冲击耐压": "1000VAC  50/60Hz 60s",
          "响应时间": "≤5ms",
          "重复精度": "≤5%Sr",
          "指示灯": "黄色LED",
          "保护": "极性保护，浪涌保护,短路保护",
          "环境温度": "-5℃～+55℃(35 to 85% RH)",
          "防护等级": "IP55",
          "连接方式": "2m  PVC电缆(三线）",
          "外壳材质": "ABS",
          "感应面材质": "滤光镜片"
        }
      }
    },
    "安装尺寸": {
      "text": "GE31ST对射/GE31SD漫反射",
      "img": "http://www.coolmay.com/kindeditor/attached/image/20210817/20210817090641_3285.jpg;"
    }
  },
  "超细激光传感器": {
    "产品名称": "超细激光传感器",
    "产品图片": "http://www.coolmay.com/kindeditor/attached/image/myUpload/DzMSEr202185101437.jpg",
    "产品特点": "1.超细，直径M3-M5；2.采用激光光源，光斑小，可以检测细小的物体；3.对检测物的范围广，金属与非金属物体都可以被感应，感应距离长，从30-130mm,对射距离可达20m;4.漫反射型产品可针对安装现场对感应距离进行一定范围的调整；5.指示灯黄色；6.电气接线为直流3线式连接；7.外壳防护等级为IP67;8.带短路，极性和浪涌保护功能；9.壳采用不锈钢材质；10.符合标准GB/T14048.10",
    "产品参数": {
      "型 号": {
        "JM3": {
          "模式": "漫反射",
          "直流型": {
            "NPN": {
              "NO": "JM3GD30DP1",
              "NC": "JM3GD30DP2"
            },
            "PNP": {
              "NO": "JM3GD30DP1",
              "NC": "JM3GD30DP2"
            }
          },
          "检测距离": "30mm内可调",
          "响应频率": ">100Hz",
          "光斑大小": "1.0mm小光点",
          "工作电压": "10-30VDC",
          "指示灯": "黄色LED",
          "光源": "红光660nm",
          "温漂": "<10%Sr",
          "负载电流": "<150mA",
          "电压降": "<1.5V",
          "漏电流": "<0.1mA",
          "响应时间": "5ms",
          "电流损耗": "<10mA",
          "回差范围": "≤15%Sr",
          "重复精度": "≤5%Sr",
          "保护": "极性保护，浪涌保护,短路保护",
          "环境温度": "-5℃～+55℃",
          "防护等级": "IP65",
          "连接方式": "2m  PVC电缆(三线）",
          "外壳材质": "不锈钢",
          "感应面材质": "滤光镜片"
        },
        "JM3_(1)": {
          "模式": "漫反射",
          "直流型": {
            "NPN": {
              "NO": "JM3GD40DP1",
              "NC": "JM3GD40DP2"
            },
            "PNP": {
              "NO": "JM3GD40DP1",
              "NC": "JM3GD40DP2"
            }
          },
          "检测距离": "40mm内可调",
          "响应频率": ">100Hz",
          "光斑大小": "1.0mm小光点",
          "工作电压": "10-30VDC",
          "指示灯": "黄色LED",
          "光源": "红光660nm",
          "温漂": "<10%Sr",
          "负载电流": "<150mA",
          "电压降": "<1.5V",
          "漏电流": "<0.1mA",
          "响应时间": "5ms",
          "电流损耗": "<10mA",
          "回差范围": "≤15%Sr",
          "重复精度": "≤5%Sr",
          "保护": "极性保护，浪涌保护,短路保护",
          "环境温度": "-5℃～+55℃",
          "防护等级": "IP65",
          "连接方式": "2m  PVC电缆(三线）",
          "外壳材质": "不锈钢",
          "感应面材质": "滤光镜片"
        },
        "JM3_(2)": {
          "模式": "对射",
          "直流型": {
            "NPN": {
              "NO": "JM3GT20000DP1",
              "NC": "JM3GT20000DP2"
            },
            "PNP": {
              "NO": "JM3GT20000DP1",
              "NC": "JM3GT20000DP2"
            }
          },
          "检测距离": "20米",
          "响应频率": ">100Hz",
          "光斑大小": "1.0mm小光点",
          "工作电压": "10-30VDC",
          "指示灯": "黄色LED",
          "光源": "红光660nm",
          "温漂": "<10%Sr",
          "负载电流": "<150mA",
          "电压降": "<1.5V",
          "漏电流": "<0.1mA",
          "响应时间": "5ms",
          "电流损耗": "<10mA",
          "回差范围": "≤15%Sr",
          "重复精度": "≤5%Sr",
          "保护": "极性保护，浪涌保护,短路保护",
          "环境温度": "-5℃～+55℃",
          "防护等级": "IP65",
          "连接方式": "2m  PVC电缆(三线）",
          "外壳材质": "不锈钢",
          "感应面材质": "滤光镜片"
        },
        "JM4": {
          "模式": "漫反射",
          "直流型": {
            "NPN": {
              "NO": "JM4GD50DP1",
              "NC": "JM4GD50DP2"
            },
            "PNP": {
              "NO": "JM4GD50DP1",
              "NC": "JM4GD50DP2"
            }
          },
          "检测距离": "50mm内可调",
          "响应频率": ">100Hz",
          "光斑大小": "1.0mm小光点",
          "工作电压": "10-30VDC",
          "指示灯": "黄色LED",
          "光源": "红光660nm",
          "温漂": "<10%Sr",
          "负载电流": "<150mA",
          "电压降": "<1.5V",
          "漏电流": "<0.1mA",
          "响应时间": "5ms",
          "电流损耗": "<10mA",
          "回差范围": "≤15%Sr",
          "重复精度": "≤5%Sr",
          "保护": "极性保护，浪涌保护,短路保护",
          "环境温度": "-5℃～+55℃",
          "防护等级": "IP65",
          "连接方式": "2m  PVC电缆(三线）",
          "外壳材质": "不锈钢",
          "感应面材质": "滤光镜片"
        },
        "JM4_(1)": {
          "模式": "漫反射",
          "直流型": {
            "NPN": {
              "NO": "JM4GD70DP1",
              "NC": "JM4GD70DP2"
            },
            "PNP": {
              "NO": "JM4GD70DP1",
              "NC": "JM4GD70DP2"
            }
          },
          "检测距离": "70mm内可调",
          "响应频率": ">100Hz",
          "光斑大小": "1.0mm小光点",
          "工作电压": "10-30VDC",
          "指示灯": "黄色LED",
          "光源": "红光660nm",
          "温漂": "<10%Sr",
          "负载电流": "<150mA",
          "电压降": "<1.5V",
          "漏电流": "<0.1mA",
          "响应时间": "5ms",
          "电流损耗": "<10mA",
          "回差范围": "≤15%Sr",
          "重复精度": "≤5%Sr",
          "保护": "极性保护，浪涌保护,短路保护",
          "环境温度": "-5℃～+55℃",
          "防护等级": "IP65",
          "连接方式": "2m  PVC电缆(三线）",
          "外壳材质": "不锈钢",
          "感应面材质": "滤光镜片"
        },
        "JM4_(2)": {
          "模式": "对射",
          "直流型": {
            "NPN": {
              "NO": "JM4GT20000DP1",
              "NC": "JM4GT20000DP2"
            },
            "PNP": {
              "NO": "JM4GT20000DP1",
              "NC": "JM4GT20000DP2"
            }
          },
          "检测距离": "20米",
          "响应频率": ">100Hz",
          "光斑大小": "1.0mm小光点",
          "工作电压": "10-30VDC",
          "指示灯": "黄色LED",
          "光源": "红光660nm",
          "温漂": "<10%Sr",
          "负载电流": "<150mA",
          "电压降": "<1.5V",
          "漏电流": "<0.1mA",
          "响应时间": "5ms",
          "电流损耗": "<10mA",
          "回差范围": "≤15%Sr",
          "重复精度": "≤5%Sr",
          "保护": "极性保护，浪涌保护,短路保护",
          "环境温度": "-5℃～+55℃",
          "防护等级": "IP65",
          "连接方式": "2m  PVC电缆(三线）",
          "外壳材质": "不锈钢",
          "感应面材质": "滤光镜片"
        },
        "JM5": {
          "模式": "漫反射",
          "直流型": {
            "NPN": {
              "NO": "JM5GD100DP1",
              "NC": "JM5GD100DP2"
            },
            "PNP": {
              "NO": "JM5GD100DP1",
              "NC": "JM5GD100DP2"
            }
          },
          "检测距离": "100mm内可调",
          "响应频率": ">100Hz",
          "光斑大小": "1.0mm小光点",
          "工作电压": "10-30VDC",
          "指示灯": "黄色LED",
          "光源": "红光660nm",
          "温漂": "<10%Sr",
          "负载电流": "<150mA",
          "电压降": "<1.5V",
          "漏电流": "<0.1mA",
          "响应时间": "5ms",
          "电流损耗": "<10mA",
          "回差范围": "≤15%Sr",
          "重复精度": "≤5%Sr",
          "保护": "极性保护，浪涌保护,短路保护",
          "环境温度": "-5℃～+55℃",
          "防护等级": "IP65",
          "连接方式": "2m  PVC电缆(三线）",
          "外壳材质": "不锈钢",
          "感应面材质": "滤光镜片"
        },
        "JM5_(1)": {
          "模式": "漫反射",
          "直流型": {
            "NPN": {
              "NO": "JM5GD130DP1",
              "NC": "JM5GD130DP2"
            },
            "PNP": {
              "NO": "JM5GD130DP1",
              "NC": "JM5GD130DP2"
            }
          },
          "检测距离": "130mm内可调",
          "响应频率": ">100Hz",
          "光斑大小": "1.0mm小光点",
          "工作电压": "10-30VDC",
          "指示灯": "黄色LED",
          "光源": "红光660nm",
          "温漂": "<10%Sr",
          "负载电流": "<150mA",
          "电压降": "<1.5V",
          "漏电流": "<0.1mA",
          "响应时间": "5ms",
          "电流损耗": "<10mA",
          "回差范围": "≤15%Sr",
          "重复精度": "≤5%Sr",
          "保护": "极性保护，浪涌保护,短路保护",
          "环境温度": "-5℃～+55℃",
          "防护等级": "IP65",
          "连接方式": "2m  PVC电缆(三线）",
          "外壳材质": "不锈钢",
          "感应面材质": "滤光镜片"
        },
        "JM5_(2)": {
          "模式": "对射",
          "直流型": {
            "NPN": {
              "NO": "JM5GT20000DP1",
              "NC": "JM5GT20000DP2"
            },
            "PNP": {
              "NO": "JM5GT20000DP1",
              "NC": "JM5GT20000DP2"
            }
          },
          "检测距离": "20米",
          "响应频率": ">100Hz",
          "光斑大小": "1.0mm小光点",
          "工作电压": "10-30VDC",
          "指示灯": "黄色LED",
          "光源": "红光660nm",
          "温漂": "<10%Sr",
          "负载电流": "<150mA",
          "电压降": "<1.5V",
          "漏电流": "<0.1mA",
          "响应时间": "5ms",
          "电流损耗": "<10mA",
          "回差范围": "≤15%Sr",
          "重复精度": "≤5%Sr",
          "保护": "极性保护，浪涌保护,短路保护",
          "环境温度": "-5℃～+55℃",
          "防护等级": "IP65",
          "连接方式": "2m  PVC电缆(三线）",
          "外壳材质": "不锈钢",
          "感应面材质": "滤光镜片"
        }
      }
    },
    "安装尺寸": {
      "text": "JM3漫反射            JM3对射JM4漫反射            JM4对射JM5漫反射            JM5对射",
      "img": "http://www.coolmay.com/kindeditor/attached/image/20210816/20210816173906_7096.jpg;http://www.coolmay.com/kindeditor/attached/image/20210816/20210816173915_4034.jpg;http://www.coolmay.com/kindeditor/attached/image/20210816/20210816173951_8318.jpg;http://www.coolmay.com/kindeditor/attached/image/20210816/20210816174001_0704.jpg;http://www.coolmay.com/kindeditor/attached/image/20210816/20210816174023_1803.jpg;http://www.coolmay.com/kindeditor/attached/image/20210816/20210816174032_3936.jpg;"
    }
  },
  "方型激光传感器": {
    "产品名称": "方型激光传感器",
    "产品图片": "http://www.coolmay.com/kindeditor/attached/image/myUpload/IqLHRe202185101457.jpg",
    "产品特点": "1.方型外型美观，结构紧凑；2.采用激光光源，光斑小，可以检测小的物体；3.对检测物的范围广，金属与非金属物体都可以被感应，感应距离长，从200-200mm,对射距离可达20m;4.漫反射型产品可针对安装现场对感应距离进行一定范围的调整；5.指示灯黄色；6.电气接线为直流3线式连接；7.外壳防护等级为IP65;8.带短路，极性和浪涌保护功能；9.壳采用BPT材质；10.符合标准GB/T14048.10",
    "产品参数": {
      "型 号": {
        "JM6": {
          "模式": "漫反射",
          "直流型": {
            "NPN": {
              "NO": "JM6GD150DP1",
              "NC": "JM6GD150DP2"
            },
            "PNP": {
              "NO": "JM6GD150DP1",
              "NC": "JM6GD150DP2"
            }
          },
          "检测距离": "150mm内可调",
          "响应频率": ">100Hz",
          "光斑大小": "2.0-3.0mm小光点",
          "工作电压": "10-30VDC",
          "指示灯": "黄色LED",
          "光源": "红光660nm",
          "温漂": "<10%Sr",
          "负载电流": "<150mA",
          "漏电流": "<0.1mA",
          "电压降": "<1.5V",
          "响应时间": "5ms",
          "电流损耗": "<10mA",
          "回差范围": "≤15%Sr",
          "重复精度": "≤5%Sr",
          "保护": "极性保护，浪涌保护,短路保护",
          "环境温度": "-5℃～+55℃",
          "防护等级": "IP65",
          "连接方式": "2m  PVC电缆(三线）",
          "外壳材质": "不锈钢",
          "感应面材质": "滤光镜片"
        },
        "JM6_(1)": {
          "模式": "漫反射",
          "直流型": {
            "NPN": {
              "NO": "JM6GD200DP1",
              "NC": "JM6GD200DP2"
            },
            "PNP": {
              "NO": "JM6GD200DP1",
              "NC": "JM6GD200DP2"
            }
          },
          "检测距离": "200mm内可调",
          "响应频率": ">100Hz",
          "光斑大小": "2.0-3.0mm小光点",
          "工作电压": "10-30VDC",
          "指示灯": "黄色LED",
          "光源": "红光660nm",
          "温漂": "<10%Sr",
          "负载电流": "<150mA",
          "漏电流": "<0.1mA",
          "电压降": "<1.5V",
          "响应时间": "5ms",
          "电流损耗": "<10mA",
          "回差范围": "≤15%Sr",
          "重复精度": "≤5%Sr",
          "保护": "极性保护，浪涌保护,短路保护",
          "环境温度": "-5℃～+55℃",
          "防护等级": "IP65",
          "连接方式": "2m  PVC电缆(三线）",
          "外壳材质": "不锈钢",
          "感应面材质": "滤光镜片"
        },
        "JM6_(2)": {
          "模式": "对射",
          "直流型": {
            "NPN": {
              "NO": "JM6GT20000DP1",
              "NC": "JM6GT20000DP2"
            },
            "PNP": {
              "NO": "JM6GT20000DP1",
              "NC": "JM6GT20000DP2"
            }
          },
          "检测距离": "20米",
          "响应频率": ">100Hz",
          "光斑大小": "2.0-3.0mm小光点",
          "工作电压": "10-30VDC",
          "指示灯": "黄色LED",
          "光源": "红光660nm",
          "温漂": "<10%Sr",
          "负载电流": "<150mA",
          "漏电流": "<0.1mA",
          "电压降": "<1.5V",
          "响应时间": "5ms",
          "电流损耗": "<10mA",
          "回差范围": "≤15%Sr",
          "重复精度": "≤5%Sr",
          "保护": "极性保护，浪涌保护,短路保护",
          "环境温度": "-5℃～+55℃",
          "防护等级": "IP65",
          "连接方式": "2m  PVC电缆(三线）",
          "外壳材质": "不锈钢",
          "感应面材质": "滤光镜片"
        },
        "JM8": {
          "模式": "漫反射",
          "直流型": {
            "NPN": {
              "NO": "JM8D150DP1",
              "NC": "JM8D150DP2"
            },
            "PNP": {
              "NO": "JM8D150DP1",
              "NC": "JM8D150DP2"
            }
          },
          "检测距离": "150mm内可调",
          "响应频率": ">100Hz",
          "光斑大小": "2.0-3.0mm小光点",
          "工作电压": "10-30VDC",
          "指示灯": "黄色LED",
          "光源": "红光660nm",
          "温漂": "<10%Sr",
          "负载电流": "<150mA",
          "漏电流": "<0.1mA",
          "电压降": "<1.5V",
          "响应时间": "5ms",
          "电流损耗": "<10mA",
          "回差范围": "≤15%Sr",
          "重复精度": "≤5%Sr",
          "保护": "极性保护，浪涌保护,短路保护",
          "环境温度": "-5℃～+55℃",
          "防护等级": "IP65",
          "连接方式": "2m  PVC电缆(三线）",
          "外壳材质": "铜镀镍",
          "感应面材质": "滤光镜片"
        },
        "JM8_(1)": {
          "模式": "漫反射",
          "直流型": {
            "NPN": {
              "NO": "JM8D200DP1",
              "NC": "JM8D200DP2"
            },
            "PNP": {
              "NO": "JM8D200DP1",
              "NC": "JM8D200DP2"
            }
          },
          "检测距离": "200mm内可调",
          "响应频率": ">100Hz",
          "光斑大小": "2.0-3.0mm小光点",
          "工作电压": "10-30VDC",
          "指示灯": "黄色LED",
          "光源": "红光660nm",
          "温漂": "<10%Sr",
          "负载电流": "<150mA",
          "漏电流": "<0.1mA",
          "电压降": "<1.5V",
          "响应时间": "5ms",
          "电流损耗": "<10mA",
          "回差范围": "≤15%Sr",
          "重复精度": "≤5%Sr",
          "保护": "极性保护，浪涌保护,短路保护",
          "环境温度": "-5℃～+55℃",
          "防护等级": "IP65",
          "连接方式": "2m  PVC电缆(三线）",
          "外壳材质": "铜镀镍",
          "感应面材质": "滤光镜片"
        },
        "JM8_(2)": {
          "模式": "对射",
          "直流型": {
            "NPN": {
              "NO": "JM8T20000DP1",
              "NC": "JM8T20000DP2"
            },
            "PNP": {
              "NO": "JM8T20000DP1",
              "NC": "JM8T20000DP2"
            }
          },
          "检测距离": "20米",
          "响应频率": ">100Hz",
          "光斑大小": "2.0-3.0mm小光点",
          "工作电压": "10-30VDC",
          "指示灯": "黄色LED",
          "光源": "红光660nm",
          "温漂": "<10%Sr",
          "负载电流": "<150mA",
          "漏电流": "<0.1mA",
          "电压降": "<1.5V",
          "响应时间": "5ms",
          "电流损耗": "<10mA",
          "回差范围": "≤15%Sr",
          "重复精度": "≤5%Sr",
          "保护": "极性保护，浪涌保护,短路保护",
          "环境温度": "-5℃～+55℃",
          "防护等级": "IP65",
          "连接方式": "2m  PVC电缆(三线）",
          "外壳材质": "铜镀镍",
          "感应面材质": "滤光镜片"
        },
        "JE31": {
          "模式": "漫反射",
          "直流型": {
            "NPN": {
              "NO": "JE31SD200DP1",
              "NC": "JE31SD200DP2"
            },
            "PNP": {
              "NO": "JE31SD200DP1",
              "NC": "JE31SD200DP2"
            }
          },
          "检测距离": "200mm内可调",
          "响应频率": ">100Hz",
          "光斑大小": "2.0-3.0mm小光点",
          "工作电压": "10-30VDC",
          "指示灯": "黄色LED",
          "光源": "红光660nm",
          "温漂": "<10%Sr",
          "负载电流": "<150mA",
          "漏电流": "<0.1mA",
          "电压降": "<1.5V",
          "响应时间": "5ms",
          "电流损耗": "<10mA",
          "回差范围": "≤15%Sr",
          "重复精度": "≤5%Sr",
          "保护": "极性保护，浪涌保护,短路保护",
          "环境温度": "-5℃～+55℃",
          "防护等级": "IP55",
          "连接方式": "2m  PVC电缆(三线）",
          "外壳材质": "ABS",
          "感应面材质": "滤光镜片"
        },
        "JE31_(1)": {
          "模式": "漫反射",
          "直流型": {
            "NPN": {
              "NO": "JE31SD300DP1",
              "NC": "JE31SD300DP2"
            },
            "PNP": {
              "NO": "JE31SD300DP1",
              "NC": "JE31SD300DP2"
            }
          },
          "检测距离": "300mm内可调",
          "响应频率": ">100Hz",
          "光斑大小": "2.0-3.0mm小光点",
          "工作电压": "10-30VDC",
          "指示灯": "黄色LED",
          "光源": "红光660nm",
          "温漂": "<10%Sr",
          "负载电流": "<150mA",
          "漏电流": "<0.1mA",
          "电压降": "<1.5V",
          "响应时间": "5ms",
          "电流损耗": "<10mA",
          "回差范围": "≤15%Sr",
          "重复精度": "≤5%Sr",
          "保护": "极性保护，浪涌保护,短路保护",
          "环境温度": "-5℃～+55℃",
          "防护等级": "IP55",
          "连接方式": "2m  PVC电缆(三线）",
          "外壳材质": "ABS",
          "感应面材质": "滤光镜片"
        },
        "JE31_(2)": {
          "模式": "对射",
          "直流型": {
            "NPN": {
              "NO": "JE31ST20000DP1",
              "NC": "JE31ST20000DP2"
            },
            "PNP": {
              "NO": "JE31ST20000DP1",
              "NC": "JE31ST20000DP2"
            }
          },
          "检测距离": "20米",
          "响应频率": "1100Hz",
          "光斑大小": "2.0-3.0mm小光点",
          "工作电压": "10-30VDC",
          "指示灯": "黄色LED",
          "光源": "红光660nm",
          "温漂": "<10%Sr",
          "负载电流": "<150mA",
          "漏电流": "<0.1mA",
          "电压降": "<1.5V",
          "响应时间": "5ms",
          "电流损耗": "<10mA",
          "回差范围": "≤15%Sr",
          "重复精度": "≤5%Sr",
          "保护": "极性保护，浪涌保护,短路保护",
          "环境温度": "-5℃～+55℃",
          "防护等级": "IP55",
          "连接方式": "2m  PVC电缆(三线）",
          "外壳材质": "ABS",
          "感应面材质": "滤光镜片"
        }
      }
    },
    "安装尺寸": {
      "text": "JM6漫反射            JM6对射JM8漫反射            JM8对射JE31漫反射和对射",
      "img": "http://www.coolmay.com/kindeditor/attached/image/20210816/20210816175019_7773.jpg;http://www.coolmay.com/kindeditor/attached/image/20210816/20210816175029_8109.jpg;http://www.coolmay.com/kindeditor/attached/image/20210816/20210816175056_8520.jpg;http://www.coolmay.com/kindeditor/attached/image/20210816/20210816175105_8758.jpg;http://www.coolmay.com/kindeditor/attached/image/20210816/20210816175120_9789.jpg;"
    }
  }
}